Workbook

Sheet Hackathons
A1: # | B1: Hackathon Name | C1: Organizers | D1: Date | E1: Duration | F1: Duration Unit | G1: Award | H1: Industry / Theme | I1: Solution | J1: Team Members | K1: Product Name | L1: Client | M1: Country | N1: Location | O1: Source Code | P1: Event Link | Q1: Award Type | R1: Additional Info | S1: Cash-equivalent Amount | T1: Cash-equivalent Currency | U1: Credit Amount | V1: Credit Currency / Units | W1: Subscription Count | X1: Subscription Amount | Y1: Subscription Currency | Z1: Other Non-cash Prize | AA1: Physical Asset | AB1: Trophy Count | AC1: Funding Amount | AD1: Funding Currency | AE1: Cash-equivalent Treatment | AF1: Review Note | AG1: Award Summary | AH1: Hackathon Team Members | AI1: Prize Allocation
A2: 1 | B2: Education Technology Hackathon | C2: Biipmi Pte Ltd | D2: 1st Sep - 3rd Sept 2016 | E2: 3 | F2: Days | G2: First Place, 18k SGD seed Funding | H2: Education | I2: Work Place Learning Solution | J2: Hazni (Biz Dev), Cheryl (Marketing), David 01-02 (01, 02) (Educator), Sayyid (UI/UX) | K2: Xueyiyi V1.0 | L2: - | M2: Singapore | N2: Lifelong Learning Institute / Scape | O2: - | P2: - | Q2: 1st Place | AC2: 18000 | AD2: SGD | AE2: Exclude | AF2: Funding, not a cash prize | AG2: 1st Place — S$18,000 Seed Funding | AH2: =IF(OR(J2="",J2="-"),"",LEN(J2)-LEN(SUBSTITUTE(J2,",",""))+1) -> 5 | AI2: Per Team
A3: 2 | B3: Innovplus 2016 2nd Quarter | C3: Inlab | D3: Sep - Oct 2016 | E3: 1 | F3: Month | G3: - | H3: Education | I3: Work Place Learning Solution | J3: Hazni (Biz Dev), David 01-02 (01, 02) (Educator & PM), Sayyid (UI/UX) | K3: Xueyiyi V2.0 | L3: Colleads, SMER, Prince | M3: Singapore | N3: Lifelong Learning Institute | O3: - | P3: - | AH3: =IF(OR(J3="",J3="-"),"",LEN(J3)-LEN(SUBSTITUTE(J3,",",""))+1) -> 4
A4: 3 | B4: DataDriven Hackathon 2016 | C4: Keeboola Asia & CodingGirls | D4: 42644 | E4: 2 | F4: Days | G4: *rated best project | H4: Property Management, Data Analytics | I4: Increase Conversion Rate for PropertyGuru | J4: Yishu See, Sayyid, Wilson Chua, Gaille Teo, Ryan, Nicholas Ling | K4: PropertyGuru Smart Algorithm | L4: PropertyGuru | M4: Singapore | N4: NUS | O4: - | P4: - | Q4: Best Project | R4: Rated best project | AE4: Exclude | AF4: Recognition only | AG4: Best Project | AH4: =IF(OR(J4="",J4="-"),"",LEN(J4)-LEN(SUBSTITUTE(J4,",",""))+1) -> 6 | AI4: Per Team
A5: 4 | B5: Fintech Festival Hackathon 2016 | C5: ByteAcademy & IBM | D5: 42675 | E5: 3 | F5: Days | G5: 1st Place, Best Use of IBM Bluemix, US$100,000 IBM Bluemix Credits, SmartWatch | H5: Fintech | I5: Tackle Financial Inclusion with data-science | J5: Roger, Wilson Chua, Aaron Gong, Sayyid | K5: SocialCapitalAsia | L5: Bank of Mangaladan | M5: Singapore | N5: Singapore Expo | O5: - | P5: - | Q5: 1st Place | R5: Best Use of IBM Bluemix | U5: 100000 | V5: USD | Z5: IBM Bluemix credits; SmartWatch | AA5: SmartWatch | AB5: 0 | AE5: Exclude | AF5: US$100,000 IBM Bluemix credit value | AG5: 1st Place — Best Use of IBM Bluemix — US$100,000 IBM Bluemix Credits — SmartWatch | AH5: =IF(OR(J5="",J5="-"),"",LEN(J5)-LEN(SUBSTITUTE(J5,",",""))+1) -> 4 | AI5: Per Team
A6: 5 | B6: Edu-Tech Hackathon 2017 | C6: NUS Edu-tech | D6: 42767 | E6: 2 | F6: Days | G6: - | H6: Education | I6: Improve learning via ML/DL | J6: Mathilde Gaucher, Xiao Heng, Raimie Tang, Sayyid | K6: SayWhat | L6: NUS | M6: Singapore | N6: NUS | O6: - | P6: - | AH6: =IF(OR(J6="",J6="-"),"",LEN(J6)-LEN(SUBSTITUTE(J6,",",""))+1) -> 4
A7: 6 | B7: SO.IMPACT Bootcamp 2017 | C7: Scape/DBS/UnFramed | D7: Feb - Mar 2017 | E7: 3 | F7: Weeks | G7: - | H7: Fintech | I7: Tackle Financial Inclusion with data-science | J7: Roger, Wilson Chua, Aaron Gong, Sayyid, Gayan Wiharagoda | K7: SocialCapitalAsia | L7: Bank of Mangaladan | M7: Singapore | N7: Scape | O7: - | P7: - | AH7: =IF(OR(J7="",J7="-"),"",LEN(J7)-LEN(SUBSTITUTE(J7,",",""))+1) -> 5
A8: 7 | B8: #UNITEDWEHACK – Empower Women 2017 | C8: AngelHack, Spacemob, GA | D8: 42826 | E8: 2 | F8: Days | G8: - | H8: Logistics & Delivery | I8: Last-mile delivery service in third-world countries | J8: Ann, Shi Yang, Sayyid, Leon | K8: Vanita | L8: - | M8: Singapore | N8: Spacemob | O8: - | P8: - | AH8: =IF(OR(J8="",J8="-"),"",LEN(J8)-LEN(SUBSTITUTE(J8,",",""))+1) -> 4
A9: 8 | B9: NUS Data Hackathon 2017 | C9: NUS | D9: 42856 | E9: 2 | F9: Days | G9: - | H9: Healthcare | I9: Face-mapping health analysis | J9: Celine Lim, Eric, Sayyid | K9: Vainster | L9: - | M9: Singapore | N9: NUS | O9: - | P9: - | AH9: =IF(OR(J9="",J9="-"),"",LEN(J9)-LEN(SUBSTITUTE(J9,",",""))+1) -> 3
A10: 9 | B10: #BOT Hackathon – Bosch IOT 2017 | C10: Bosch | D10: 42856 | E10: 2 | F10: Days | G10: - | H10: Healthcare | I10: Notifier Mailer system | J10: Anna Tantushyan, Eileen Chua, Singaram, Sayyid | K10: Mailbox IOT system | L10: - | M10: Singapore | N10: Block 71 | O10: - | P10: - | AH10: =IF(OR(J10="",J10="-"),"",LEN(J10)-LEN(SUBSTITUTE(J10,",",""))+1) -> 4
A11: 10 | B11: DataDriven Hackathon 2017 | C11: Keeboola Asia | D11: 42979 | E11: 2 | F11: Days | G11: *rated best project | H11: Various, Data Analytics | I11: App for expats/home movers | J11: Sayyid, Ilas, Gene | K11: Swagmylife | L11: PropertyGuru, Esplanade, Tabsquare | M11: Singapore | N11: Facebook APAC 2017 | O11: - | P11: - | Q11: Best Project | R11: Rated best project | AE11: Exclude | AF11: Recognition only | AG11: Best Project | AH11: =IF(OR(J11="",J11="-"),"",LEN(J11)-LEN(SUBSTITUTE(J11,",",""))+1) -> 3 | AI11: Per Team
A12: 11 | B12: SUTD Whatthehack Hackathon 2017 | C12: SUTD | D12: 43009 | E12: 2 | F12: Days | G12: - | H12: Edu-Fintech, Data Analytics | I12: Student budget/lifestyle optimizer | J12: Sayyid, Mortiz, Terry, Hendry | K12: Warriors&Mages | L12: - | M12: Singapore | N12: SUTD | O12: - | P12: - | AH12: =IF(OR(J12="",J12="-"),"",LEN(J12)-LEN(SUBSTITUTE(J12,",",""))+1) -> 4
A13: 12 | B13: Intuition Hackathon 2017 | C13: NTU | D13: 43009 | E13: 2 | F13: Days | G13: - | H13: Edu-Fintech, Data Analytics | I13: Impact investment search tool | J13: Daryll (Biz Dev), Sayyid (Design/Tech), Edward, Matthew Tan (Design/Tech) | K13: Nestash | L13: Blackrock | M13: Singapore | N13: NTU | O13: - | P13: - | AH13: =IF(OR(J13="",J13="-"),"",LEN(J13)-LEN(SUBSTITUTE(J13,",",""))+1) -> 4
A14: 13 | B14: Hack&Roll 2018 | C14: NUS | D14: 43101 | E14: 2 | F14: Days | G14: - | H14: Personal Development, Data Analytics | I14: Time optimization analytics | J14: Jet New, Sayyid | K14: Life-Worth Evaluator | L14: - | M14: Singapore | N14: NUS | O14: - | P14: - | AH14: =IF(OR(J14="",J14="-"),"",LEN(J14)-LEN(SUBSTITUTE(J14,",",""))+1) -> 2
A15: 14 | B15: #SPSEC SP Hackathon 2018 | C15: SP | D15: 43160 | E15: 1 | F15: Days | G15: 3rd Place, $100 Capitaland voucher | H15: Food, Health & Fitness | I15: Dietary food locator | J15: Sayyid, Hong Wei | K15: Smart Food Bridge | L15: - | M15: Singapore | N15: SP | O15: - | P15: - | Q15: 3rd Place | S15: 100 | T15: SGD | Z15: S$100 Capitaland voucher | AE15: Yes | AF15: Voucher counted as cash equivalent | AG15: 3rd Place — S$100 Capitaland Voucher Each | AH15: =IF(OR(J15="",J15="-"),"",LEN(J15)-LEN(SUBSTITUTE(J15,",",""))+1) -> 2 | AI15: Per Team Member
A16: 15 | B16: #FOSSASIA SP Hackathon 2018 | C16: FOSSASIA | D16: 43160 | E16: 2 | F16: Days | G16: - | H16: Weather, Data Analytics | I16: Rain-to-flood probability analytics | J16: syabiqah phang, Jason Choo Yan Sheng, Sayyid | K16: Weather Guru | L16: FOSSASIA | M16: Singapore | N16: Lifelong Learning Institute | O16: - | P16: - | AH16: =IF(OR(J16="",J16="-"),"",LEN(J16)-LEN(SUBSTITUTE(J16,",",""))+1) -> 3
A17: 16 | B17: #SmartCity Hackathon 2018 | C17: Energo | D17: 43191 | E17: 2 | F17: Days | G17: - | H17: Social Enterprise, E-Waste | I17: E-waste collection for elderly empowerment | J17: Bobby Lim, Willie | K17: Goblin (E-Waste Collector) | L17: - | M17: Singapore | N17: NTU Alumni Club | O17: - | P17: - | AH17: =IF(OR(J17="",J17="-"),"",LEN(J17)-LEN(SUBSTITUTE(J17,",",""))+1) -> 2
A18: 17 | B18: #Mosque-Tech Challenge 2018 | C18: Mendaki | D18: 43252 | E18: 2 | F18: Days | G18: 2nd Place, $600 cash | H18: Fintech, Shariah Compliance | I18: Shariah-compliant investment analyzer | J18: Matthew Tan, Sayyid, Jay | K18: iceigloo | L18: - | M18: Singapore | N18: Muhajirin Mosque | O18: - | P18: - | Q18: 2nd Place | S18: 600 | T18: SGD | AE18: Yes | AF18: Explicit cash | AG18: 2nd Place — S$600 Cash | AH18: =IF(OR(J18="",J18="-"),"",LEN(J18)-LEN(SUBSTITUTE(J18,",",""))+1) -> 3 | AI18: Per Team
A19: 18 | B19: #WSG HR Hackathon 2018 | C19: Padang.co | D19: Sep 8-9, 2018 | E19: 2 | F19: Days | G19: - | H19: Human Resource | I19: Job description optimizer | J19: Jun Ting, Lucas Grey, Sayyid, Benjamin Chong | K19: Checker App | L19: - | M19: Singapore | N19: Mapletree Business City | O19: - | P19: - | AH19: =IF(OR(J19="",J19="-"),"",LEN(J19)-LEN(SUBSTITUTE(J19,",",""))+1) -> 4
A20: 19 | B20: #NTU Intuition Hackathon 2018 | C20: NTU | D20: Oct 13-14, 2018 | E20: 2 | F20: Days | G20: - | H20: Fintech, Financial Legacy | I20: Open-source digital will planner | J20: Gia, Timothy John, Balint, Sayyid | K20: Fasight | L20: - | M20: Singapore | N20: NTU (The Arc – North Spine) | O20: - | P20: - | AH20: =IF(OR(J20="",J20="-"),"",LEN(J20)-LEN(SUBSTITUTE(J20,",",""))+1) -> 4
A21: 20 | B21: #NASA Space Hackathon 2018 | C21: Padang.co & NASA | D21: Oct 20-21, 2018 | E21: 2 | F21: Days | G21: - | H21: Space | I21: Data visualization app | J21: Heng Pei, Evan, Yu Ning, Jason Choo Yan Sheng, Sayyid | K21: CO2unter | L21: - | M21: Singapore | N21: Mapletree Business City | O21: - | P21: - | AH21: =IF(OR(J21="",J21="-"),"",LEN(J21)-LEN(SUBSTITUTE(J21,",",""))+1) -> 5
A22: 21 | B22: #SP Smart Nation Hackathon 2018 | C22: SP | D22: Nov 10, 2018 | E22: 2 | F22: Days | G22: - | H22: Smart Nation / Social Good | I22: Group food recommendation app | J22: David 21-23-24-25 (21, 23, 24, 25), Matthew Tan, Sayyid | K22: WinWinCusine | L22: - | M22: Singapore | N22: Singapore Poly (LT18A) | O22: - | P22: - | AH22: =IF(OR(J22="",J22="-"),"",LEN(J22)-LEN(SUBSTITUTE(J22,",",""))+1) -> 6
A23: 22 | B23: Super Silly Hackathon 2018 | C23: GoJek | D23: Dec 15, 2018 | E23: 2 | F23: Days | G23: - | H23: Afterlife | I23: Shoe burial service | J23: Sayyid | K23: ShoeObituaries | L23: - | M23: Singapore | N23: GoJek Office (38 Sin Ming Ln) | O23: - | P23: - | AH23: =IF(OR(J23="",J23="-"),"",LEN(J23)-LEN(SUBSTITUTE(J23,",",""))+1) -> 1
A24: 23 | B24: #NUS Hack&Roll 2019 | C24: NUS | D24: Jan 19-20, 2019 | E24: 2 | F24: Days | G24: - | H24: Pest Busting | I24: IoT pest detector | J24: Sayyid, Kyren, Matthew Tan, David 21-23-24-25 (21, 23, 24, 25) | K24: PestOverflow | L24: - | M24: Singapore | N24: NUS | O24: - | P24: - | AH24: =IF(OR(J24="",J24="-"),"",LEN(J24)-LEN(SUBSTITUTE(J24,",",""))+1) -> 7
A25: 24 | B25: #HACKNTU 2019 | C25: NTU | D25: Jan 19-20, 2019 | E25: 2 | F25: Days | G25: - | H25: Smart Nation | I25: Gym location analytics | J25: Sayyid, Kenneth, Matthew Tan, David 21-23-24-25 (21, 23, 24, 25) | K25: MyNextGym | L25: - | M25: Singapore | N25: NTU (The ARC – North Spine) | O25: - | P25: - | AH25: =IF(OR(J25="",J25="-"),"",LEN(J25)-LEN(SUBSTITUTE(J25,",",""))+1) -> 7
A26: 25 | B26: #Mosque Hackathon 2019 | C26: An-Nur Mosque | D26: May 19-20, 2019 | E26: 2 | F26: Days | G26: 3rd Place, $500 SGD cash | H26: Healthy Living | I26: Mnemonics for memory retention | J26: Sayyid, Matthew Tan, David 21-23-24-25 (21, 23, 24, 25) | K26: NeuroSurge | L26: Mendaki | M26: Singapore | N26: An-Nur Mosque | O26: - | P26: - | Q26: 3rd Place | S26: 500 | T26: SGD | AE26: Yes | AF26: Explicit cash | AG26: 3rd Place — S$500 Cash | AH26: =IF(OR(J26="",J26="-"),"",LEN(J26)-LEN(SUBSTITUTE(J26,",",""))+1) -> 6 | AI26: Per Team
A27: 26 | B27: #Flutter Hackathon 2019 | C27: Flutter & PSLOVE | D27: Jun 1, 2019 | E27: 1 | F27: Days | G27: - | H27: Education / Linguistics | I27: Language exchange platform | J27: Sayyid, Kamil, Kashif, Aseem Wangoo, Arthur | K27: Amigo | L27: - | M27: Singapore | N27: Block 71 | O27: - | P27: - | AH27: =IF(OR(J27="",J27="-"),"",LEN(J27)-LEN(SUBSTITUTE(J27,",",""))+1) -> 5
A28: 27 | B28: #AngelHack 2019 | C28: AngelHack, AWS, IBM, Grab | D28: Jun 6-7, 2019 | E28: 2 | F28: Days | G28: - | H28: Fintech | I28: E-credits via GrabPoints | J28: Sayyid, Jason Choo Yan Sheng, Kang Liang Koh, Ashraf | K28: GrabHunt | L28: - | M28: Singapore | N28: PSB Academy STEM Campus | O28: - | P28: - | AH28: =IF(OR(J28="",J28="-"),"",LEN(J28)-LEN(SUBSTITUTE(J28,",",""))+1) -> 4
A29: 28 | B29: #SWSG 2019 | C29: Startup Weekend SG | D29: Sep 6-8, 2019 | E29: 2.5 | F29: Days | G29: - | H29: Waste Management / Sustainability | I29: Gamified recycling app | J29: Sayyid, Jason Choo Yan Sheng, Bobby Lim, Maureen | K29: Kitar-GO | L29: - | M29: Singapore | N29: SCAPE (Level 5) | O29: - | P29: - | AH29: =IF(OR(J29="",J29="-"),"",LEN(J29)-LEN(SUBSTITUTE(J29,",",""))+1) -> 4
A30: 29 | B30: #HACKNTU 2019 | C30: Intuition 6.0 | D30: Oct 12-13, 2019 | E30: 2 | F30: Days | G30: - | H30: Waste Management / Sustainability | I30: Home waste-picking robot | J30: Sayyid, Matthew Tan, Sin Mei Chong, Zi Cing Sim | K30: MyNextGym | L30: - | M30: Singapore | N30: NTU | O30: - | P30: - | AH30: =IF(OR(J30="",J30="-"),"",LEN(J30)-LEN(SUBSTITUTE(J30,",",""))+1) -> 4
A31: 30 | B31: Super Silly Hackathon 2019 | C31: Carousell | D31: Dec 14, 2019 | E31: 1 | F31: Days | G31: - | H31: Silly Solutions | I31: Couple expectation manager (Angel/Devil concept) | J31: Sayyid, Haley | K31: The Punisher | L31: - | M31: Singapore | N31: Carousell @ Keppel Towers 2 | O31: - | P31: - | AH31: =IF(OR(J31="",J31="-"),"",LEN(J31)-LEN(SUBSTITUTE(J31,",",""))+1) -> 2
A32: 31 | B32: Mosque Tech Challenge 2023 | C32: Al-Falah Mosque | D32: Apr 15-16, 2023 | E32: 2 | F32: Days | G32: - | H32: Wellness / Healthcare | I32: Career/learning/mental health tracker | J32: Sayyid, Iskandar Zulkarnain, Hakam, Hakim | K32: GrowthGuru | L32: - | M32: Singapore | N32: Al-Falah Mosque | O32: - | P32: - | AH32: =IF(OR(J32="",J32="-"),"",LEN(J32)-LEN(SUBSTITUTE(J32,",",""))+1) -> 4
A33: 32 | B33: ICP Ideathon 2023 | C33: ICP | D33: Dec 17-18, 2023 | E33: 2 | F33: Days | H33: Productivity | I33: Web3 jargon summarizer (Instagram-style) | J33: Sayyid, Iskandar Zulkarnain | K33: Instareadr | L33: ICP | M33: Singapore | N33: Cineleisure Orchard | O33: - | P33: - | AH33: =IF(OR(J33="",J33="-"),"",LEN(J33)-LEN(SUBSTITUTE(J33,",",""))+1) -> 2
A34: 33 | B34: ICP Ideathon 2023 | C34: ICP | D34: Dec 17-18, 2023 | E34: 2 | F34: Days | G34: 3rd Prize (S$250 Cash) | H34: Productivity | I34: Decentralized website builder on ICP blockchain | J34: Sayyid, Jimmy Peh | K34: Structur3 | L34: ICP | M34: Singapore | N34: Cineleisure Orchard | O34: - | P34: - | Q34: 3rd Place | S34: 250 | T34: SGD | AE34: Yes | AF34: Confirmed cash | AG34: 3rd Place — S$250 Cash | AH34: =IF(OR(J34="",J34="-"),"",LEN(J34)-LEN(SUBSTITUTE(J34,",",""))+1) -> 2 | AI34: Per Team
A35: 34 | B35: Builder Together: AI Hackathon 2024 | C35: Antler | D35: Jun 6-7, 2024 | E35: 2 | F35: Days | G35: - | H35: Education | I35: AI quiz generator from videos (enterprise) | J35: Sayyid, Arav Behl, Manas | K35: LrnMate | L35: - | M35: Singapore | N35: 128 Princep Street, Singapore | O35: https://github.com/arav-behl/LrnMate/tree/main | P35: - | AH35: =IF(OR(J35="",J35="-"),"",LEN(J35)-LEN(SUBSTITUTE(J35,",",""))+1) -> 3
A36: 35 | B36: Mosque Tech Challenge 2025 | C36: Al-Mawaddah Mosque | D36: Mar 22-23, 2025 | E36: 2 | F36: Days | G36: 2nd Prize (S$1,000 Cash) | H36: Family | I36: Father-child bonding app (Gen AI adventures) | J36: Sayyid, Adib Yusof, Ali Marzuki, Hilsann Yong | K36: AnginOmbak | L36: - | M36: Singapore | N36: Al-Mawaddah Mosque | O36: https://github.com/sayyidkhan/anginombak | P36: - | Q36: 2nd Place | S36: 1000 | T36: SGD | AE36: Yes | AF36: Confirmed cash | AG36: 2nd Place — S$1,000 Cash | AH36: =IF(OR(J36="",J36="-"),"",LEN(J36)-LEN(SUBSTITUTE(J36,",",""))+1) -> 4 | AI36: Per Team
A37: 36 | B37: Super AI Hackathon 2025 | C37: Super AI | D37: Jun 17-19, 2025 | E37: 3 | F37: Days | G37: - | H37: Open Track | I37: AI consulting for SMEs (McKinsey-style) | J37: Joewin Tan, Sayyid, Lester Cheong, Wan Wei | K37: UpsacleAI | L37: Super AI Hackathon | M37: Singapore | N37: Marina Bay Sands | O37: http://github.com/cheonglol/superai-next-hackathon-2025 | P37: - | AH37: =IF(OR(J37="",J37="-"),"",LEN(J37)-LEN(SUBSTITUTE(J37,",",""))+1) -> 4
A38: 37 | B38: Bolt.New Hackathon 2025 | C38: Virtual | D38: Jun 21, 2025 | E38: 1 | F38: Days | G38: - | H38: Open Track | I38: AI consulting for SMEs (v2) | J38: Joewin Tan, Sayyid, Lester Cheong, Wan Wei | K38: UpsacleAI [Bolt Edition] | L38: bolt.new | M38: Singapore | N38: Virtual | O38: https://devpost.com/software/jslw-scaleupai-bolt-edition | P38: - | AH38: =IF(OR(J38="",J38="-"),"",LEN(J38)-LEN(SUBSTITUTE(J38,",",""))+1) -> 4
A39: 38 | B39: OOJU X Manus.AI Hackathon 2025 | C39: Manus | D39: Jun 27, 2025 | E39: 1 | F39: Days | G39: 2nd Prize (Manus Pro Subscription) | H39: Virtual Reality | I39: AI consulting for SMEs (VR edition) | J39: Joewin Tan, Sayyid, Lester Cheong, Wan Wei | K39: UpsacleAI [VR Edition] | L39: OOJU & Manus.ai | M39: Singapore | N39: SQ Collective | O39: https://github.com/sayyidkhan/manus-im-hackathon | P39: - | Q39: 2nd Prize | W39: 1 | X39: 39 | Y39: USD | Z39: Manus Pro subscription | AE39: Exclude | AF39: US$39 monthly value at award period | AG39: 2nd Place — Manus Pro Subscription (US$39/month each) | AH39: =IF(OR(J39="",J39="-"),"",LEN(J39)-LEN(SUBSTITUTE(J39,",",""))+1) -> 4 | AI39: Per Team Member
A40: 39 | B40: Emergency GPT hackathon 2025 | C40: The TGB Collective | D40: Aug 10, 2025 | E40: 1 | F40: Days | G40: - | H40: Open Track | I40: chatgpt 6 nano | J40: sayyid, ivan | K40: chatgpt-6-nano | L40: - | M40: Singapore | N40: SQ Collective | O40: https://github.com/sayyidkhan/gpt6-nano | P40: - | AH40: =IF(OR(J40="",J40="-"),"",LEN(J40)-LEN(SUBSTITUTE(J40,",",""))+1) -> 2
A41: 40 | B41: Sarawak AI Hackathon 2025 | C41: Sarawak X Singapore | D41: Sep 6, 2025 | E41: 1 | F41: Days | G41: Novel Hackathon Finisher — Trophy | H41: Design | J41: Hisyam, Hafidz | K41: - | L41: Singapore X Sarawak | M41: Sarawak | N41: Makeramai Makerspace, Kuching, Sarawak, Malaysia | O41: - | P41: - | Q41: Novel Hackathon Finisher | Z41: Trophy | AA41: Trophy | AB41: 1 | AE41: Exclude | AF41: Trophy, not cash | AG41: Novel Hackathon Finisher — Trophy | AH41: =IF(OR(J41="",J41="-"),"",LEN(J41)-LEN(SUBSTITUTE(J41,",",""))+1) -> 2 | AI41: Per Team
A42: 41 | B42: NAS.IO Hackathon 2025 | C42: NAS.io | D42: 45920 | E42: 1 | F42: Days | G42: - | H42: Advertising | I42: Learn how to build a funnel using nas.io platform | J42: sayyid | K42: - | M42: Singapore | N42: SMU | O42: https://github.com/sayyidkhan/prompt-alchemist-beta | P42: - | AH42: =IF(OR(J42="",J42="-"),"",LEN(J42)-LEN(SUBSTITUTE(J42,",",""))+1) -> 1
A43: 42 | B43: Nosana Hackathon 2025 | C43: Nosana | D43: 45930 | E43: 1 | F43: Days | G43: 1st Prize, $500 Nosana Cloud Credit | H43: ML Inference | I43: Built a moon trading app, trade crypto according to moon cycles | J43: sayyid | K43: AstroDegen | L43: Nosana | M43: Singapore | N43: Monk Brew House | O43: https://github.com/sayyidkhan/nosana-ci-agent-challenge | P43: - | Q43: 1st Prize | U43: 500 | V43: USD | Z43: Nosana Cloud credit | AE43: Exclude | AF43: Cloud credit, not cash | AG43: 1st Place — US$500 Nosana Cloud Credits | AH43: =IF(OR(J43="",J43="-"),"",LEN(J43)-LEN(SUBSTITUTE(J43,",",""))+1) -> 1 | AI43: Per Team
A44: 43 | B44: Airia Hackathon 2025 | C44: Airia | D44: 45932 | E44: 1 | F44: Days | G44: - | H44: Formula 1 | I44: Built a formula 1 betting app | J44: sayyid | K44: F1 Degens | L44: - | M44: Singapore | N44: SQ Collective | O44: - | P44: - | AH44: =IF(OR(J44="",J44="-"),"",LEN(J44)-LEN(SUBSTITUTE(J44,",",""))+1) -> 1
A45: 44 | B45: Cursor Hackathon Singapore 2025 | C45: Cursor | D45: Oct 18-19, 2025 | E45: 2 | F45: Days | G45: - | H45: Open Track | I45: Vibe Trading App | J45: sayyid, hisyam, hafidz, shashi | K45: Vibewater Associates | L45: OpenAI, Antrohpic, convex, cursor, fal.ai | M45: Singapore | N45: SUTD | O45: https://github.com/sayyidkhan/vibewater_associates | P45: - | AH45: =IF(OR(J45="",J45="-"),"",LEN(J45)-LEN(SUBSTITUTE(J45,",",""))+1) -> 4
A46: 45 | B46: Cloudflare Hackathon 2025 | C46: Cloudflare | D46: 45954 | E46: 1 | F46: Days | G46: - | H46: Open Track | I46: Vibe Coding Addiction Tool | J46: sayyid, cy, jun kai, ajentik | K46: Asterix | L46: Cloudflare & Redis | M46: Singapore | N46: Cloudflare Office Singapore | O46: https://github.com/sayyidkhan/asterix | P46: - | AH46: =IF(OR(J46="",J46="-"),"",LEN(J46)-LEN(SUBSTITUTE(J46,",",""))+1) -> 4
A47: 46 | B47: Singhack Hackathon 2025 | C47: Singhacks | D47: 31Oct - 2 Nov, 2025 | E47: 2.5 | F47: Days | G47: - | H47: Blockchain | I47: Agentic Ai ecosystem on hedera blockchain | J47: sayyid, shashi, brian, marcus | K47: Hedera Agents Hub | L47: Hedera | M47: Singapore | N47: catapult by capitaland | O47: https://github.com/sayyidkhan/HederaAgentsHub | P47: - | AH47: =IF(OR(J47="",J47="-"),"",LEN(J47)-LEN(SUBSTITUTE(J47,",",""))+1) -> 4
A48: 47 | B48: Lovable & ANCHR 2025 | C48: Lovable | D48: Nov 22-23, 2025 | E48: 2 | F48: Days | G48: - | H48: Open Track | I48: Tempeh shaped computer parts | J48: sayyid | K48: Natalie's Tempeh | L48: Lovable | M48: Singapore | N48: Remote | O48: https://github.com/sayyidkhan/nataliestempeh | P48: - | AH48: =IF(OR(J48="",J48="-"),"",LEN(J48)-LEN(SUBSTITUTE(J48,",",""))+1) -> 1
A49: 48 | B49: Lovable & ANCHR 2025 | C49: Lovable | D49: Nov 22-23, 2025 | E49: 2 | F49: Days | G49: - | H49: Open Track | I49: Gen AI Greeting Card Generator | J49: sayyid, Sofia Kung | K49: jollycard | L49: Lovable | M49: Singapore | N49: Remote | O49: https://github.com/sayyidkhan/jollycards | P49: - | AH49: =IF(OR(J49="",J49="-"),"",LEN(J49)-LEN(SUBSTITUTE(J49,",",""))+1) -> 2
A50: 49 | B50: APAC’s First Art x Tech Hackathon | C50: Yee / Amanda / Elie / Joe / Jass | D50: 24/1/2026 | E50: 1 | F50: Days | G50: - | H50: Curated Theme: Touch Grass | I50: Stress Out, Bunny In: A gentle interactive space to stop working and start resting. | J50: sayyid,shashi,hisyam | K50: Stress Out,Bunny In | L50: Thoth AI, Airfoil, Elevenlabs, V0, Figma, OpenAI, Lovable, SMU | M50: Singapore | N50: SMU Connexion | O50: https://github.com/sayyidkhan/art-x-tech-hackathon-2026 | P50: https://luma.com/186w8zoo?tk=Y3hTyJ | AH50: =IF(OR(J50="",J50="-"),"",LEN(J50)-LEN(SUBSTITUTE(J50,",",""))+1) -> 3
A51: 50 | B51: Agentfield Hackathon 2026 | C51: AI Builders | D51: 46205 | E51: 1 | F51: Days | G51: 1st Prize (OpenRouter Credits $1000 USD) | H51: Agentic AI | I51: MagiStock → Autonomous Portfolio Risk Governor | J51: sayyid,shashi,clement | K51: MagiStock | L51: Agentfield | M51: Singapore | N51: Monk Brew House | O51: https://github.com/sayyidkhan/agentfields | P51: https://luma.com/afsghackathon | Q51: 1st Prize | U51: 1000 | V51: USD | Z51: OpenRouter credits | AE51: Exclude | AF51: API credits, not cash | AG51: 1st Place — US$1,000 OpenRouter Credits | AH51: =IF(OR(J51="",J51="-"),"",LEN(J51)-LEN(SUBSTITUTE(J51,",",""))+1) -> 3 | AI51: Per Team
A52: 51 | B52: Agentfield Hackathon 2026 | C52: AI Builders | D52: 46205 | E52: 1 | F52: Days | G52: - | H52: Agentic AI | I52: Build an Agentic AI to help you to determine to quit your job | J52: sayyid,shashi,clement | K52: Should I Quit | L52: Agentfield | M52: Singapore | N52: Monk Brew House | O52: https://github.com/sayyidkhan/shouldIquit | P52: https://luma.com/afsghackathon | AH52: =IF(OR(J52="",J52="-"),"",LEN(J52)-LEN(SUBSTITUTE(J52,",",""))+1) -> 3
A53: 52 | B53: AgentForce Hackathon 2026 | C53: AI Builders | D53: 28/2/2026 | E53: 1 | F53: Days | G53: 1st Prize (API Credits $500 USD) | H53: Agentic AI | I53: Track 1: A multimodal AI application that generates complete LinkedIn launch packages | J53: sayyid,shashi,hisyam | K53: AI LinkedIn Launch Studio | L53: WaveSpeed AI, Zeabur, Qoder, Insforge | M53: Singapore | N53: NUS | O53: https://github.com/sayyidkhan/agent-forge-track1 | P53: https://luma.com/sgaihackthon?tk=9KBC0q | Q53: 1st Prize | U53: 500 | V53: USD | Z53: API credits | AE53: Exclude | AF53: API credits, not cash | AG53: 1st Place — US$500 API Credits | AH53: =IF(OR(J53="",J53="-"),"",LEN(J53)-LEN(SUBSTITUTE(J53,",",""))+1) -> 3 | AI53: Per Team
A54: 53 | B54: AgentForce Hackathon 2026 | C54: AI Builders | D54: 28/2/2026 | E54: 1 | F54: Days | G54: 1st Prize (API Credits $500 USD) | H54: Agentic AI | I54: Track 2: Compares two public professional profiles in an anime-style 1vs1 battle. | J54: sayyid,shashi,hisyam | K54: DevDuel Agent | L54: Bright Data, ActionBook, Acontext | M54: Singapore | N54: NUS | O54: https://github.com/sayyidkhan/agent-forge-track2 | P54: https://luma.com/sgaihackthon?tk=9KBC0q | Q54: 1st Prize | U54: 500 | V54: USD | Z54: API credits | AE54: Exclude | AF54: API credits, not cash | AG54: 1st Place — US$500 API Credits | AH54: =IF(OR(J54="",J54="-"),"",LEN(J54)-LEN(SUBSTITUTE(J54,",",""))+1) -> 3 | AI54: Per Team
A55: 54 | B55: SUSS X Openclaw Hackathon 2026 | C55: Singapore Opensourced Hub, Wavespeed AI, Minimax, Mem u | D55: 13/3/2026 | E55: 1 | F55: Days | G55: 1st Prize (Wavespeed AI Credits $150 USD) | H55: Events | I55: Gigradar - AI agents that discover and verify live events across the internet. | J55: sayyid,Clarence Chan,zhang cheng | K55: Gigradar | L55: - | M55: Singapore | N55: SUSS | O55: - | P55: https://luma.com/sourceawakening?tk=HdsoHg | Q55: 1st Prize | U55: 150 | V55: USD | Z55: Wavespeed AI credits | AE55: Exclude | AF55: API credits, not cash | AG55: 1st Place — US$150 Wavespeed AI Credits | AH55: =IF(OR(J55="",J55="-"),"",LEN(J55)-LEN(SUBSTITUTE(J55,",",""))+1) -> 3 | AI55: Per Team
A56: 55 | B56: TinyFish SG Hackathon 2026 | C56: TinyFish | D56: 28/3/2026 | E56: 1 | F56: Days | G56: - | H56: Events | I56: Buzo - Your AI Concierage for live events worldwide | J56: sayyid,Clarence Chan,zhang cheng | K56: Buzo | L56: - | M56: Singapore | N56: NUS | O56: - | P56: https://luma.com/4n1e9si9?tk=I1WSBi | AH56: =IF(OR(J56="",J56="-"),"",LEN(J56)-LEN(SUBSTITUTE(J56,",",""))+1) -> 3
A57: 56 | B57: January Capital Hackathon SG 2026 | C57: January Capital & OpenAI | D57: 46207 | E57: 1 | F57: Days | G57: - | H57: Events | I57: Bryan Feedback Agent - An Agent that collects high quailty event feedback after an event | J57: sayyid/Clarence Chan | K57: Bryan Feedback Agent | L57: - | M57: Singapore | N57: NUS | O57: https://github.com/gigradarapp/gr-bryan-feedback-agent | P57: https://luma.com/wn9f2gta?tk=iqBwSL | AH57: =IF(OR(J57="",J57="-"),"",LEN(J57)-LEN(SUBSTITUTE(J57,",",""))+1) -> 1
A58: 57 | B58: Agora.io Voice AI Hackathon Singapore 2026 | C58: Agora.io | D58: 46299 | E58: 1 | F58: Days | G58: 3rd Prize: S$300 Cash and S$385 worth of API Credits | H58: Agentic AI (Voice), Healthcare | I58: Speak your symptoms. Get your MC. Skip the queue. | J58: sayyid | K58: Medivoice | L58: - | M58: Singapore | N58: Carousell Campus (Regional HQ) | O58: https://github.com/sayyidkhan/agora-medihealth | P58: https://luma.com/89t0ejof?tk=jjk7Rp | Q58: 3rd Prize | S58: 300 | T58: SGD | U58: 385 | V58: SGD | Z58: API credits | AE58: Yes | AF58: Explicit cash; API credit value also tracked | AG58: 3rd Place — S$300 Cash + S$385 API Credits | AH58: =IF(OR(J58="",J58="-"),"",LEN(J58)-LEN(SUBSTITUTE(J58,",",""))+1) -> 1 | AI58: Per Team
A59: 58 | B59: MeDo Singapore Vibe Coding Hackathon 2026 | C59: MeDo Singapore | D59: 18/4/2026 | E59: 1 | F59: Days | G59: - | H59: Human Resource | I59: HackAtlas —Mapping the world’s top hackathon builders. | J59: sayyid,zhang cheng, elena xiao | K59: HackAtlas | L59: MeDo | M59: Singapore | N59: NUS | O59: https://devpost.com/software/1248526/joins/rd1pZGiClia_sxEWA0RNJg | P59: https://luma.com/sgvibecodinghackathon?tk=vDly3i | AH59: =IF(OR(J59="",J59="-"),"",LEN(J59)-LEN(SUBSTITUTE(J59,",",""))+1) -> 3
A60: 59 | B60: Temasek Hackathon 2026 | C60: Temasek, Antrophic, Genspark | D60: 24/4/2026 | E60: 1 | F60: Days | G60: - | H60: Project Management | I60: AI that detects and fixes workflow bottlenecks | J60: sayyid,shashi,ryan foo | K60: Brain Org | L60: - | M60: Singapore | N60: Temasek ShopHouse | O60: https://devfolio.co/projects/ontrack-ai-7d28 | P60: https://push-to-prod.devfolio.co/overview | AH60: =IF(OR(J60="",J60="-"),"",LEN(J60)-LEN(SUBSTITUTE(J60,",",""))+1) -> 3
A61: 60 | B61: Build Voice Agents with Speechmatics | TGB Buildathon 2026 | C61: Speechmatics | D61: 29/4/2026 | E61: 1 | F61: Days | G61: 2K USD Speechmatics Credits | H61: Agentic AI (Voice) | I61: Build Voice Agents with Speechmatics | TGB Buildathon | J61: sayyid | K61: Guardian Agent | L61: - | M61: Singapore | N61: SGInnovate | O61: https://github.com/sayyidkhan/guardian-agent | P61: https://luma.com/tgbspeechmatics1?tk=NaV6RE | Q61: Award | R61: Speechmatics | U61: 2000 | V61: USD | Z61: Speechmatics credits | AE61: Exclude | AF61: USD-denominated credit value | AG61: Award — Speechmatics — US$2,000 Speechmatics Credits | AH61: =IF(OR(J61="",J61="-"),"",LEN(J61)-LEN(SUBSTITUTE(J61,",",""))+1) -> 1 | AI61: Per Team
A62: 61 | B62: Vercel Zero to Agent: Singapore (1 Hr Hackathon) 2026 | C62: v0, Vercel | D62: 30/4/2026 | E62: 1 | F62: Days | G62: 2nd Place — v0 Sock | H62: Game | I62: build the ultimate data center empire | J62: sayyid | K62: Data Center Tycoon [Web Only] | L62: - | M62: Singapore | N62: SQ Collective | O62: - | P62: https://luma.com/bh5iqhnx?tk=17u8ZH | Q62: 2nd Place | R62: v0 Sock | Z62: v0 Sock | AA62: v0 Sock | AB62: 0 | AE62: Exclude | AF62: Physical item, not cash | AG62: 2nd Place — v0 Sock | AH62: =IF(OR(J62="",J62="-"),"",LEN(J62)-LEN(SUBSTITUTE(J62,",",""))+1) -> 1 | AI62: Per Team
A63: 62 | B63: Emergency GPT hackathon 2026 | C63: openai | D63: 46085 | E63: 1 | F63: Hours | G63: - | H63: Events | I63: Buzo (Ai Search) Feature - Personalised Event Searching | J63: sayyid,Clarence Chan,zhang cheng | K63: Ask Buzo | L63: - | M63: Singapore | N63: Open Sourced Café | O63: https://github.com/gigradarapp/gr-ask-buzo | P63: https://luma.com/zprbhtzy?tk=gMcrjt | AH63: =IF(OR(J63="",J63="-"),"",LEN(J63)-LEN(SUBSTITUTE(J63,",",""))+1) -> 3
A64: 63 | B64: Vercel Zero to Agent: Global 2026 | C64: v0, Vercel | D64: 46116 | E64: 1 | F64: Days | G64: - | H64: Game | I64: build the ultimate data center empire (now mobile optimised) | J64: sayyid | K64: Data Center Tycoon [Web + Mobile Edition] | L64: - | M64: Singapore | N64: Remote | O64: https://github.com/sayyidkhan/v0-data-center-tycoon | P64: https://community.vercel.com/hackathons/zero-to-agent | AH64: =IF(OR(J64="",J64="-"),"",LEN(J64)-LEN(SUBSTITUTE(J64,",",""))+1) -> 1
A65: 64 | B65: aie hackathon 2026 | C65: 65 labs | D65: 46270 | E65: 1 | F65: Days | G65: - | H65: Game | I65: build the ultimate data center destroyer | J65: sayyid,hisyam,jazli,hafidz | K65: Data Center Destroyer | L65: - | M65: Singapore | N65: NUS | O65: https://github.com/sayyidkhan/data-center-destroyer | P65: https://luma.com/aie-hack?tk=6ESqwa | AH65: =IF(OR(J65="",J65="-"),"",LEN(J65)-LEN(SUBSTITUTE(J65,",",""))+1) -> 4
A66: 65 | B66: Ralphthon SG 2026 | C66: SuperTeam SG,Hashed,Petani | D66: 17/5/26 | E66: 1 | F66: Days | G66: - | H66: Agentic AI | I66: Voice-first backend harness that turns spoken software ideas into structured Codex tasks, then coordinates a builder worker and streams progress back to the user. | J66: sayyid | K66: Mums Can Build | L66: - | M66: Singapore | N66: Suntec Tower 1 | O66: https://github.com/sayyidkhan/mums-can-build | P66: https://luma.com/4hx7p0vs?tk=ruRx4s | AH66: =IF(OR(J66="",J66="-"),"",LEN(J66)-LEN(SUBSTITUTE(J66,",",""))+1) -> 1
A67: 66 | B67: UCWS 2026 (Semi-Finals) | C67: Epic Connector | D67: 1/5/2026 - 30/5/2026 | E67: 1 | F67: Month | G67: Top 20, 10K USD OpenAI Credits, 2K USD Gemini Cloud Credits | H67: Events | I67: Buzo - Your AI Concierage for live events worldwide | J67: sayyid,Clarence Chan | K67: Buzo 2.0 | L67: - | M67: Singapore | N67: Remote | O67: - | P67: - | Q67: Top 20 | U67: 12000 | V67: USD | Z67: 10K OpenAI credits; 2K Gemini Cloud credits | AE67: Exclude | AF67: Credit value total combines two USD-denominated credits | AG67: Top 20 — US$12,000 Credits (OpenAI + Gemini Cloud) | AH67: =IF(OR(J67="",J67="-"),"",LEN(J67)-LEN(SUBSTITUTE(J67,",",""))+1) -> 2 | AI67: Per Team
A68: 67 | B68: Super AI Hackathon 2026 | C68: Super AI | D68: 9/6/2026 - 11/6/2026 | E68: 3 | F68: Days | G68: - | H68: Movie | I68: Agentic AI + VR - Talk to the movie characters | J68: sayyid,Mickael Martin Carapiet,Akdora Celepoglu | K68: SceneVerse AI | L68: SuperAI | M68: Singapore | N68: Marina Bay Sands | O68: https://github.com/sayyidkhan/agentic-vr-frontend | P68: - | AH68: =IF(OR(J68="",J68="-"),"",LEN(J68)-LEN(SUBSTITUTE(J68,",",""))+1) -> 3
A69: 68 | B69: UCWS 2026 (Finals) | C69: Epic Connector | D69: 13/6/2026 | E69: 1 | F69: Days | G69: - | H69: Events | I69: Buzo - Your AI Concierage for live events worldwide | J69: sayyid,Clarence Chan | K69: Buzo 2.1 | L69: - | M69: Singapore | N69: 8 George St, Pickering Operations Complex | O69: - | P69: https://luma.com/UCWS2026?tk=y5h4YG | AH69: =IF(OR(J69="",J69="-"),"",LEN(J69)-LEN(SUBSTITUTE(J69,",",""))+1) -> 2
A70: 69 | B70: Zo Computer Jun 2026 Build Challenge | C70: Zo Computer | D70: 20 Jun - 21 Jun 2026 | E70: 2 | F70: Days | H70: productivity | I70: A lightweight storefront and payment-proof order tracker for small businesses, deployed on Zo Computer. | J70: sayyid,Hao Ming,Bruce Chua,aslam | K70: Zo Order Tracker | L70: Zo Computer | M70: US | N70: Remote | O70: https://github.com/sayyidkhan/zo-order-tracker | P70: https://ambassador.zo.space/build-challenge | AH70: =IF(OR(J70="",J70="-"),"",LEN(J70)-LEN(SUBSTITUTE(J70,",",""))+1) -> 4
A71: 70 | B71: Sup Build2026 Hackathon | C71: Sup | D71: 27/6/2026 | E71: 1 | F71: Days | G71: - | H71: productivity | I71: Live career opportunity and relationship mapper powered by OpenAI and Exa | J71: sayyid | K71: zo relationship mapper | L71: Sup | M71: Singapore | N71: Suntec Tower 1 | O71: https://github.com/sayyidkhan/zo-relationship-mapper | P71: https://luma.com/zda76sc1?tk=f30DS9 | AH71: =IF(OR(J71="",J71="-"),"",LEN(J71)-LEN(SUBSTITUTE(J71,",",""))+1) -> 1
A72: 71 | B72: BUIDL_OPC_Hackathon_SG | C72: amber.ac | D72: 46363 | E72: 1 | F72: Days | G72: Top 30 — US$4,500 AWS Credits | H72: Productivity | I72: kingdom of pal: 7 dwarfs and a shiekh, a tool to help maange one person community biz | J72: sayyid,Bruce Chua | K72: Kingdom Of PAL | L72: amber.ac | M72: Singapore | N72: Lifelong Learning Institute | O72: - | P72: https://luma.com/r6v3evdi?tk=BuCFqn | Q72: Top 30 | U72: 4500 | V72: USD | Z72: AWS credits | AE72: Exclude | AF72: USD-denominated credit value | AG72: Top 30 — US$4,500 AWS Credits | AH72: =IF(OR(J72="",J72="-"),"",LEN(J72)-LEN(SUBSTITUTE(J72,",",""))+1) -> 2 | AI72: Per Team
A73: 72 | B73: Whackathon 2026 | C73: Folly | D73: 18/7/2026 | E73: 1 | F73: Days | G73: - | H73: Game | I73: An adventure game where an alien is trying to find its way home, each map is ai rendered | J73: sayyid | K73: Alien Homecoming | L73: Folly | M73: Singapore | N73: Terra Loft | O73: https://github.com/sayyidkhan/alien-homecoming | P73: https://luma.com/68nouvl9?tk=yuORah | AH73: =IF(OR(J73="",J73="-"),"",LEN(J73)-LEN(SUBSTITUTE(J73,",",""))+1) -> 1
A74: 73 | B74: Zo Computer Jul 2026 Build Challenge (Kill your SaaS) | C74: Zo Computer | D74: 15 Jul - 25 Jul 2026 | E74: 10 | F74: Days | G74: - | H74: Infra | I74: clone google drive together with other commonly used infra features | J74: sayyid | K74: Zo Drive | L74: Zo Computer | M74: US | N74: Remote | O74: https://github.com/sayyidkhan/zo-drive | P74: https://ambassador.zo.space/build-challenge | AH74: =IF(OR(J74="",J74="-"),"",LEN(J74)-LEN(SUBSTITUTE(J74,",",""))+1) -> 1
A75: 74 | B75: Google Buildathon 2026 (Theme: The Cooperate Telepath) | C75: Google | D75: 46150 | E75: 1 | F75: Days | G75: - | H75: Google | I75: Translating stakeholder dreams into user reality. A multi-agent feature stress-tester powered by Google ADK and Gemini. | J75: sayyid | K75: The Cooperate Telepath | L75: Google | M75: Singapore | N75: Marina Bay Sands | O75: https://github.com/sayyidkhan/the-corporate-telepath | P75: - | AH75: =IF(OR(J75="",J75="-"),"",LEN(J75)-LEN(SUBSTITUTE(J75,",",""))+1) -> 1
A76: 75 | B76: One AI Hackathon 2026 | C76: CybrDeck | D76: 15/08/2026 | E76: 1 | F76: Days | G76: Best Vertical Solution (Family Office Track), 2,000 Cybrdeck API credits (worth US$25) | H76: Family Office | I76: An Agentic Family Office for the nightlife and culture economy | J76: sayyid, clarence | K76: Buzo Atlas | L76: CybrDeck | M76: Singapore | N76: Kent Ridge, Block 71 | O76: https://github.com/gigradarapp/gr-atlas | P76: https://luma.com/e9h4kv5k?tk=lzXXdx | Q76: Best Project | R76: Best Vertical Solution: Family Office Track | U76: 25 | V76: USD | Z76: 2,000 Cybrdeck API credits | AE76: Exclude | AF76: US$25 credit value, not cash | AG76: Best Project — Best Vertical Solution: Family Office Track — 2,000 Cybrdeck API Credits Each (US$25 value) | AH76: =IF(OR(J76="",J76="-"),"",LEN(J76)-LEN(SUBSTITUTE(J76,",",""))+1) -> 2 | AI76: Per Team Member
A77: 76 | B77: Build with Gemini Hackathon 2026 | C77: 65labs, Google, Lorong AI | D77: 22/08/2026 | E77: 1 | F77: Days | G77: - | H77: Embedded Models | I77: A local-first city-management game where players govern Innovation City with Gemma as an on-device chief of staff for incident triage, guardrails, and scenario stress-testing. | J77: sayyid | K77: Agrim Tycoon | L77: Google DeepMind | M77: Singapore | N77: Lorong AI @ One-North | O77: https://github.com/sayyidkhan/agrim-tycoon | P77: https://luma.com/deepmind-v4ci?tk=LBgGrm | AH77: =IF(OR(J77="",J77="-"),"",LEN(J77)-LEN(SUBSTITUTE(J77,",",""))+1) -> 1
A78: 77 | B78: Zo Build Challenge | C78: Zo Computer | D78: 1st Aug - 31st Aug 2026 | E78: 1 | F78: Month | G78: - | H78: Build for Someone Else | I78: A personal memory experience built for someone else. | J78: sayyid | K78: Zo Memories | L78: Zo Computer | M78: US | N78: Remote | O78: https://github.com/sayyidkhan/zo-memories | P78: https://ambassador.zo.space/build-challenge | AH78: =IF(OR(J78="",J78="-"),"",LEN(J78)-LEN(SUBSTITUTE(J78,",",""))+1) -> 1
A79: 78 | B79: ChatGPT Sites Hackathon | C79: OpenAI, Gabriel Chua, Brian Chew, Zane Chee, Sherry Jiang | D79: 02/09/2026 | E79: 4 | F79: Hours | G79: - | H79: ChatGPT Sites | I79: PeterIndex is a relationship-intelligence tool that remembers people, context, and loose threads, then surfaces warm paths to the next opportunity. | J79: sayyid, han | K79: PeterIndex | L79: OpenAI | M79: Singapore | N79: Singapore | O79: https://github.com/sayyidkhan/peterindex | P79: https://luma.com/yqq0zo50?tk=kakZ3u | AH79: =IF(OR(J79="",J79="-"),"",LEN(J79)-LEN(SUBSTITUTE(J79,",",""))+1) -> 2
A80: 79 | B80: SG × SWK Friendship AI Business Design Hackathon | C80: Azam Sarawak, ANCHR AI Labs | D80: 3 Sep 2026 | E80: 2 | F80: Days | G80: Trophy, First Runner Up, SG × Sarawak AI & Design Hackathon 2026, 200 USD Kimi AI credits | H80: Micro Business | I80: A bilingual digital visitor experience for Long Taa, a Sebup longhouse village in Sarawak, with trip planning and a Kimi-powered visitor assistant. | J80: sayyid, Hao Ming, Bruce | K80: Long Taa Borneo Eco Stay | L80: Longtaa Borneo | M80: Malaysia | N80: Affin Bank Hikmah Exchange, Kuching, Sarawak | O80: https://github.com/sayyidkhan/longtaaborneo | P80: https://luma.com/n0zkb5w0?tk=OBDQgW | Q80: First Runner-Up | R80: SG × Sarawak AI & Design Hackathon 2026 | U80: 200 | V80: USD | Z80: Trophy; Kimi AI credits | AA80: Trophy | AB80: 1 | AE80: Exclude | AF80: Trophy excluded; credit value tracked | AG80: First Runner-Up — SG × Sarawak AI & Design Hackathon — US$200 Kimi AI Credits + Trophy | AH80: =IF(OR(J80="",J80="-"),"",LEN(J80)-LEN(SUBSTITUTE(J80,",",""))+1) -> 3 | AI80: Per Team
A81: 80 | B81: GPT-6 Astra Hackathon: Singapore | C81: OpenAI, Gabriel Chua, Zane Chee, Brian Chew, Sherry Jiang | D81: 13 Sep 2026 | E81: 1 | F81: Days | G81: Best use of GPT-Image-2.5, 5,000 USD OpenAI credits | H81: Agentic AI | I81: Explore a real 3D city with a flying crow, then generate AI travel scenes of yourself at your destination. | J81: sayyid, Clement Lork | K81: Itachi's Crow | L81: OpenAI | M81: Singapore | N81: Singapore | O81: https://github.com/sayyidkhan/itachiscrow | P81: https://luma.com/fdzbrq5b?tk=QX3FM2 | Q81: Best Project | R81: Best Use of GPT-Image-2.5 | U81: 5000 | V81: USD | Z81: OpenAI credits | AE81: Exclude | AF81: Credit value tracked | AG81: Best Project — Best Use of GPT-Image-2.5 — US$5,000 OpenAI Credits Each | AH81: =IF(OR(J81="",J81="-"),"",LEN(J81)-LEN(SUBSTITUTE(J81,",",""))+1) -> 2 | AI81: Per Team Member
A82: 81 | B82: Anti-Drug Jam 2026 | C82: SCOGA, Esports Academy, National Council Against Drug Abuse (NCADA) | D82: 19 Sep 2026 | E82: 1 | F82: Days | H82: Anti Drugs | I82: An illustrated storybook adventure where you sketch solutions to help Bob navigate peer pressure and find his safe way home. | J82: sayyid | K82: The Next 8 Seconds: Draw Your Way Home | L82: SCOGA × NCADA | M82: Singapore | N82: *SCAPE Ground Theatre | O82: https://github.com/sayyidkhan/8-mins | P82: https://scoga-anti-drug-jam-2026.ai.studio/ | AH82: =IF(OR(J82="",J82="-"),"",LEN(J82)-LEN(SUBSTITUTE(J82,",",""))+1) -> 1

Sheet People
A1: People & LinkedIn Directory
A2: One person per row. LinkedIn URLs are added only after the profile has been verified against the hackathon context.
A4: Person ID | B4: Name | C4: Hackathon #s | D4: Builds Together | E4: LinkedIn URL
A5: P001 | B5: Aaron Gong | C5: #004, #006 | D5: 2 | E5: https://www.linkedin.com/in/aaronjxz/
A6: P002 | B6: Adib Yusof | C6: #035 | D6: 1 | E6: https://www.linkedin.com/in/adibyusof/
A7: P003 | B7: ajentik | C7: #045 | D7: 1
A8: P004 | B8: Akdora Celepoglu | C8: #067 | D8: 1 | E8: https://www.linkedin.com/in/-akdora/
A9: P005 | B9: Ali Marzuki | C9: #035 | D9: 1 | E9: https://www.linkedin.com/in/ali-marzuki-48266542/
A10: P006 | B10: Ann | C10: #007 | D10: 1
A11: P007 | B11: Anna Tantushyan | C11: #009 | D11: 1 | E11: https://www.linkedin.com/in/annatantushyan/
A12: P008 | B12: Arav Behl | C12: #034 | D12: 1 | E12: https://www.linkedin.com/in/arav-behl/
A13: P009 | B13: Arthur | C13: #026 | D13: 1
A14: P010 | B14: Aseem Wangoo | C14: #026 | D14: 1 | E14: https://www.linkedin.com/in/aseemwangoo/
A15: P011 | B15: Ashraf | C15: #027 | D15: 1
A16: P012 | B16: aslam | C16: #069 | D16: 1 | E16: https://www.linkedin.com/in/mohamed-aslam-abdul/
A17: P013 | B17: Balint | C17: #019 | D17: 1
A18: P014 | B18: Benjamin Chong | C18: #018 | D18: 1 | E18: https://www.linkedin.com/in/chongmunhou/
A19: P015 | B19: Bobby Lim | C19: #016, #028 | D19: 2 | E19: https://www.linkedin.com/in/bobbylim93/
A20: P016 | B20: brian | C20: #046 | D20: 1
A21: P017 | B21: Bruce Chua | C21: #069, #071, #079 | D21: 3 | E21: https://www.linkedin.com/in/bruce-chua-28832a414/
A22: P018 | B22: Celine Lim | C22: #008 | D22: 1
A23: P019 | B23: Cheryl | C23: #001 | D23: 1
A24: P020 | B24: Clarence Chan | C24: #054, #055, #056, #062, #066, #068, #075 | D24: 7 | E24: https://www.linkedin.com/in/clarencechanxy/
A25: P021 | B25: Clement Lork | C25: #050, #051, #080 | D25: 3 | E25: https://www.linkedin.com/in/clement-lork/
A26: P022 | B26: cy | C26: #045 | D26: 1
A27: P023 | B27: Daryll | C27: #012 | D27: 1
A28: P024 | B28: David 01-02 | C28: #001, #002 | D28: 2
A29: P025 | B29: David 21-23-24-25 | C29: #021, #023, #024, #025 | D29: 4
A30: P026 | B30: Edward | C30: #012 | D30: 1
A31: P027 | B31: Eileen Chua | C31: #009 | D31: 1 | E31: https://www.linkedin.com/in/eileenchua926/
A32: P028 | B32: elena xiao | C32: #058 | D32: 1 | E32: https://www.linkedin.com/in/xiao-elena/
A33: P029 | B33: Eric | C33: #008 | D33: 1
A34: P030 | B34: Evan | C34: #020 | D34: 1
A35: P031 | B35: Gaille Teo | C35: #003 | D35: 1 | E35: https://www.linkedin.com/in/gaille-teo/
A36: P032 | B36: Gayan Wiharagoda | C36: #006 | D36: 1 | E36: https://www.linkedin.com/in/gayanwiharagoda/
A37: P033 | B37: Gene | C37: #010 | D37: 1
A38: P034 | B38: Gia | C38: #019 | D38: 1
A39: P035 | B39: Hafidz | C39: #040, #044, #064 | D39: 3
A40: P036 | B40: Hakam | C40: #031 | D40: 1 | E40: https://www.linkedin.com/in/abdul-hakam-bin-nor-razak-nus/
A41: P037 | B41: Hakim | C41: #031 | D41: 1 | E41: https://www.linkedin.com/in/akmal-hakim-teo/
A42: P038 | B42: Haley | C42: #030 | D42: 1
A43: P039 | B43: Hao Ming | C43: #069, #079 | D43: 2
A44: P040 | B44: Hazni | C44: #001, #002 | D44: 2 | E44: https://www.linkedin.com/in/hazniaris/
A45: P041 | B45: Hendry | C45: #011 | D45: 1
A46: P042 | B46: Heng Pei | C46: #020 | D46: 1
A47: P043 | B47: Hilsann Yong | C47: #035 | D47: 1 | E47: https://www.linkedin.com/in/hilsannyong/
A48: P044 | B48: Hisyam | C48: #040, #044, #049, #052, #053, #064 | D48: 6 | E48: https://www.linkedin.com/in/hisyamj/
A49: P045 | B49: Hong Wei | C49: #014 | D49: 1
A50: P046 | B50: Ilas | C50: #010 | D50: 1
A51: P047 | B51: Iskandar Zulkarnain | C51: #031, #032 | D51: 2 | E51: https://www.linkedin.com/in/is-z23/
A52: P048 | B52: ivan | C52: #039 | D52: 1 | E52: https://www.linkedin.com/in/ivan-hong-24a83315a/
A53: P049 | B53: Jason Choo Yan Sheng | C53: #015, #020, #027, #028 | D53: 4 | E53: https://www.linkedin.com/in/chooyansheng/
A54: P050 | B54: Jay | C54: #017 | D54: 1
A55: P051 | B55: jazli | C55: #064 | D55: 1 | E55: https://www.linkedin.com/in/ahmad-jazli/
A56: P052 | B56: Jet New | C56: #013 | D56: 1 | E56: https://www.linkedin.com/in/jetnew/
A57: P053 | B57: Jimmy Peh | C57: #033 | D57: 1 | E57: https://www.linkedin.com/in/jimmy-peh-95202251/
A58: P054 | B58: Joewin Tan | C58: #036, #037, #038 | D58: 3 | E58: https://www.linkedin.com/in/joewin-tan-speaker-and-business-owner/
A59: P055 | B59: jun kai | C59: #045 | D59: 1
A60: P056 | B60: Jun Ting | C60: #018 | D60: 1
A61: P057 | B61: Kamil | C61: #026 | D61: 1
A62: P058 | B62: Kang Liang Koh | C62: #027 | D62: 1 | E62: https://www.linkedin.com/in/klkoh/
A63: P059 | B63: Kashif | C63: #026 | D63: 1
A64: P060 | B64: Kenneth | C64: #024 | D64: 1
A65: P061 | B65: Kyren | C65: #023 | D65: 1
A66: P062 | B66: Leon | C66: #007 | D66: 1
A67: P063 | B67: Lester Cheong | C67: #036, #037, #038 | D67: 3 | E67: https://www.linkedin.com/in/lester-cheong-a29a4a209/
A68: P064 | B68: Lucas Grey | C68: #018 | D68: 1 | E68: https://www.linkedin.com/in/lucasgrey/
A69: P065 | B69: Manas | C69: #034 | D69: 1
A70: P066 | B70: marcus | C70: #046 | D70: 1
A71: P067 | B71: Mathilde Gaucher | C71: #005 | D71: 1
A72: P068 | B72: Matthew Tan | C72: #012, #017, #021, #023, #024, #025, #029 | D72: 7 | E72: https://www.linkedin.com/in/tthmatt/
A73: P069 | B73: Maureen | C73: #028 | D73: 1 | E73: https://www.linkedin.com/in/maureen-tan/
A74: P070 | B74: Mickael Martin Carapiet | C74: #067 | D74: 1 | E74: https://www.linkedin.com/in/mickaelcarapiet/
A75: P071 | B75: Mortiz | C75: #011 | D75: 1
A76: P072 | B76: Nicholas Ling | C76: #003 | D76: 1 | E76: https://www.linkedin.com/in/nicholas-ling/
A77: P073 | B77: Raimie Tang | C77: #005 | D77: 1 | E77: https://www.linkedin.com/in/raimie-tang/
A78: P074 | B78: Roger | C78: #004, #006 | D78: 2 | E78: https://www.linkedin.com/in/rogerdo/
A79: P075 | B79: Ryan | C79: #003 | D79: 1
A80: P076 | B80: ryan foo | C80: #059 | D80: 1 | E80: https://www.linkedin.com/in/foo-ryan/
A81: P077 | B81: Sayyid | C81: #001, #002, #003, #004, #005, #006, #007, #008, #009, #010, #011, #012, #013, #014, #015, #017, #018, #019, #020, #021, #022, #023, #024, #025, #026, #027, #028, #029, #030, #031, #032, #033, #034, #035, #036, #037, #038, #039, #041, #042, #043, #044, #045, #046, #047, #048, #049, #050, #051, #052, #053, #054, #055, #056, #057, #058, #059, #060, #061, #062, #063, #064, #065, #066, #067, #068, #069, #070, #071, #072, #073, #074, #075, #076, #077, #078, #079, #080, #081 | D81: 79 | E81: https://www.linkedin.com/in/sayyidkhan92/
A82: P078 | B82: shashi | C82: #044, #046, #049, #050, #051, #052, #053, #059 | D82: 8 | E82: https://www.linkedin.com/in/shashiguru-keluth-765129154/
A83: P079 | B83: Shi Yang | C83: #007 | D83: 1
A84: P080 | B84: Sin Mei Chong | C84: #029 | D84: 1
A85: P081 | B85: Singaram | C85: #009 | D85: 1 | E85: https://www.linkedin.com/in/r-singaram-047415b0/
A86: P082 | B86: Sofia Kung | C86: #048 | D86: 1 | E86: https://www.linkedin.com/in/sofiakung/
A87: P083 | B87: syabiqah phang | C87: #015 | D87: 1 | E87: https://www.linkedin.com/in/syabiqah-phang/
A88: P084 | B88: Terry | C88: #011 | D88: 1
A89: P085 | B89: Timothy John | C89: #019 | D89: 1
A90: P086 | B90: Wan Wei | C90: #036, #037, #038 | D90: 3 | E90: https://www.linkedin.com/in/sohwanwei/
A91: P087 | B91: Willie | C91: #016 | D91: 1
A92: P088 | B92: Wilson Chua | C92: #003, #004, #006 | D92: 3 | E92: https://www.linkedin.com/in/wilsonchua/
A93: P089 | B93: Xiao Heng | C93: #005 | D93: 1
A94: P090 | B94: Yishu See | C94: #003 | D94: 1 | E94: https://www.linkedin.com/in/yishu-see/
A95: P091 | B95: Yu Ning | C95: #020 | D95: 1
A96: P092 | B96: zhang cheng | C96: #054, #055, #058, #062 | D96: 4 | E96: https://www.linkedin.com/in/zhangcheng1997/
A97: P093 | B97: Zi Cing Sim | C97: #029 | D97: 1 | E97: https://www.linkedin.com/in/simzicing/
A98: P094 | B98: Han | C98: #078 | D98: 1

Sheet Socials
A1: Socials by Hackathon
A2: One row per numbered hackathon. Add only posts that clearly document the relevant build or event.
A3: Hackathon # | B3: LinkedIn | C3: Instagram | D3: Facebook
A4: #001
A5: #002
A6: #003
A7: #004
A8: #005
A9: #006
A10: #007
A11: #008
A12: #009
A13: #010
A14: #011 | C14: https://www.instagram.com/p/BZsdBDyAuNk/
A15: #012
A16: #013
A17: #014 | C17: https://www.instagram.com/p/BgWUFk4FOSa/
A18: #015 | C18: https://www.instagram.com/p/Bgvs2dLAeue/
A19: #016
A20: #017 | C20: https://www.instagram.com/p/BjogOfOA6tG/
A21: #018 | C21: https://www.instagram.com/p/BngqOFTggiI/ https://www.instagram.com/p/Bngpa4igs3o/
A22: #019 | C22: https://www.instagram.com/p/Bo6FW7zg0Zj/
A23: #020 | C23: https://www.instagram.com/p/BpMd-mignvt/ https://www.instagram.com/p/BpMRvP0g435/
A24: #021 | C24: https://www.instagram.com/p/BqADJkbAn8x/
A25: #022
A26: #023 | C26: https://www.instagram.com/p/Bs2f8FHHXNo/
A27: #024
A28: #025 | C28: https://www.instagram.com/p/Bxo5Ka1FLrR/
A29: #026 | D29: https://www.facebook.com/share/p/18y8TAM2dB/
A30: #027 | D30: https://www.facebook.com/share/p/1F5LDVBjUj/
A31: #028 | C31: https://www.instagram.com/p/B2EYk1KluTZ/ https://www.instagram.com/p/B2JzcFglegx/ | D31: https://www.facebook.com/sayyid.iskandar/posts/pfbid0rxHXvZDwNWumGZdXFgUnJiu12SW3FUwyTueeejHBw8a6tAGgyLHUFeZB8n2iNhmfl https://www.facebook.com/sayyid.iskandar/posts/pfbid02YSrksK2xzkZUh8uifPrWYxk6VHt7aMVfcef6vc1AXoauq9GTCUGQQpLDQpbUUAUyl https://www.facebook.com/share/p/1DSDV99DjY/ https://www.facebook.com/share/p/1HXZcYB6ew/ https://www.facebook.com/share/p/1BiUy52YeW/ https://www.facebook.com/share/p/1QzGUmEibA/ https://www.facebook.com/share/p/19Thtkbyvq/ https://www.facebook.com/share/p/182DHiJcRd/ https://www.facebook.com/share/p/1DeRrdfhWH/ https://www.facebook.com/share/p/1HYmuCRfuP/ https://www.facebook.com/share/p/1JmrdD1Bb7/
A32: #029 | D32: https://www.facebook.com/sayyid.iskandar/posts/pfbid02HTKxyfqPKL2uR4n9zFFxAzkXbE7FYNjkzzuQpqRpEgeCBzYnqvfko88xe9nDPD4kl https://www.facebook.com/share/v/1BNrHxPRHz/
A33: #030 | D33: https://www.facebook.com/sayyid.iskandar/posts/pfbid02T7TywvEM5ypGy8vVEQyJVS1ZAzQns7CGz483NQGZX5CKf1DaCw8P6VbcAFdQmqczl
A34: #031 | C34: https://www.instagram.com/p/CrGJq7JvfYS/
A35: #032 | C35: https://www.instagram.com/p/C0_xx0zRc1u/
A36: #033 | C36: https://www.instagram.com/p/C1E93kNxOjM/
A37: #034 | C37: https://www.instagram.com/p/C8MapmzSGnB/
A38: #035 | C38: https://www.instagram.com/p/DHlaIwwz9Qg/ https://www.instagram.com/p/DHlZp4wTHze/
A39: #036 | C39: https://www.instagram.com/p/DLBb3yoT412/ https://www.instagram.com/p/DLFWtVrx0_O/ https://www.instagram.com/reel/DLEZ4_LRK_G/ https://www.instagram.com/reel/DLEGXTsTe1y/
A40: #037 | C40: https://www.instagram.com/p/DLcXTxAxUgg/
A41: #038
A42: #039 | C42: https://www.instagram.com/p/DNLa9r_xO3o/
A43: #040 | B43: https://www.linkedin.com/feed/update/urn:li:activity:7373307701516427264/ | C43: https://www.instagram.com/p/DOQcqfMk4Wk/ https://www.instagram.com/p/DOVACxLE9PW/ https://www.instagram.com/reel/DOVLDxsE37O/ https://www.instagram.com/reel/DOQFqH8kfeT/
A44: #041 | C44: https://www.instagram.com/p/DO0q1KYky3H/
A45: #042 | C45: https://www.instagram.com/p/DPOUBvaE3GR/
A46: #043 | C46: https://www.instagram.com/p/DPbGjobkxFW/
A47: #044 | B47: https://www.linkedin.com/feed/update/urn:li:activity:7387523389042843648/ | C47: https://www.instagram.com/p/DP-pSUWjPCS/
A48: #045 | C48: https://www.instagram.com/reel/DQV0xxIk9ab/
A49: #046 | C49: https://www.instagram.com/reel/DQjw5Lik-5m/
A50: #047
A51: #048
A52: #049 | C52: https://www.instagram.com/p/DT49z3cE84y/
A53: #050 | B53: https://www.linkedin.com/feed/update/urn:li:activity:7425889935137837056/ | C53: https://www.instagram.com/p/DUdGe1jk_Wh/
A54: #051
A55: #052 | C55: https://www.instagram.com/p/DVTWt5qE6QA/
A56: #053 | C56: https://www.instagram.com/p/DVTWt5qE6QA/
A57: #054 | B57: https://www.linkedin.com/feed/update/urn:li:activity:7438474540781006848/ | C57: https://www.instagram.com/p/DV0x7PoE18a/
A58: #055 | C58: https://www.instagram.com/p/DWd1UjUkwSf/
A59: #056
A60: #057 | B60: https://www.linkedin.com/feed/update/urn:li:activity:7448758050586521600/ | C60: https://www.instagram.com/p/DW9CxfwE6Ln/ https://www.instagram.com/p/DW_vFeIk0-2/
A61: #058 | C61: https://www.instagram.com/p/DXRahaqk28d/
A62: #059 | B62: https://www.linkedin.com/feed/update/urn:li:activity:7455961388025389056/ | C62: https://www.instagram.com/p/DXg-YyWE5r6/
A63: #060 | B63: https://www.linkedin.com/feed/update/urn:li:activity:7455961388025389056/ | C63: https://www.instagram.com/p/DXwnu_3E2dI/
A64: #061 | B64: https://www.linkedin.com/feed/update/urn:li:activity:7455961388025389056/ | C64: https://www.instagram.com/p/DXwqrEOkwoB/ https://www.instagram.com/reel/DXykZomTmXD/
A65: #062 | C65: https://www.instagram.com/p/DX4HAVzE9WO/
A66: #063
A67: #064 | B67: https://www.linkedin.com/feed/update/urn:li:activity:7459414332150534144/ | C67: https://www.instagram.com/p/DYLfGwuk3Xc/
A68: #065 | B68: https://www.linkedin.com/feed/update/urn:li:activity:7462661884056416256/ | C68: https://www.instagram.com/p/DYe1dlpE7Af/
A69: #066 | B69: https://www.linkedin.com/feed/update/urn:li:activity:7471043781799178240/ | C69: https://www.instagram.com/p/DZc1D4HHbmy/ https://www.instagram.com/p/DZeIbzgRO-n/
A70: #067 | B70: https://www.linkedin.com/feed/update/urn:li:activity:7472197868632571905/ | C70: https://www.instagram.com/reel/DZom-hVRIRN/ https://www.instagram.com/reel/DZonQbURE5R/
A71: #068 | B71: https://www.linkedin.com/feed/update/urn:li:activity:7480285163512418306/ | C71: https://www.instagram.com/p/DZ3itBVzLwN/ https://www.instagram.com/p/DZ7AtfFndkJ/
A72: #069 | C72: https://www.instagram.com/p/DZ7Wj9anW7x/
A73: #070 | B73: https://www.linkedin.com/feed/update/urn:li:activity:7477508615239585792/ | C73: https://www.instagram.com/p/DaFSqK7k2ce/ https://www.instagram.com/p/DaFSaYHkwPC/ https://www.instagram.com/reel/DaFm4k2zifY/
A74: #071 | B74: https://www.linkedin.com/feed/update/urn:li:activity:7482072463900835840/ | C74: https://www.instagram.com/p/Dash2D1k4C2/
A75: #072 | B75: https://www.linkedin.com/feed/update/urn:li:activity:7486774772140474368/ | C75: https://www.instagram.com/p/DbN5kZlk0LL/ https://www.instagram.com/reel/DbN4xRaxZY8/ https://www.instagram.com/reel/DbN5OnlRCGQ/
A76: #073 | C76: https://www.instagram.com/p/DbpmfeiHexb/
A77: #074 | B77: https://www.linkedin.com/feed/update/urn:li:activity:7490764342309855232/ | C77: https://www.instagram.com/p/Db50W3FHYuM/
A78: #075 | B78: https://www.linkedin.com/posts/sayyidkhan92_hackathon-singapore-ai-activity-7495846654978478080-lNv7?utm_source=share&utm_medium=member_desktop&rcm=ACoAABzB85UB8iZMlY6hoj9K3g7MfcRKsCZOvqw | C78: https://www.instagram.com/p/DcOZh7DHVFE/
A79: #076 | B79: https://www.linkedin.com/feed/update/urn:li:activity:7498397192852779008/ | C79: https://www.instagram.com/reel/Dcgk8b_RELZ/ https://www.instagram.com/p/DcghI50ncWn/
A80: #077 | C80: https://www.instagram.com/p/Dcxszh0nbh6/
A81: #078 | C81: https://www.instagram.com/p/Dc5Nkd-nU1B/
A82: #079 | B82: https://www.linkedin.com/posts/sayyidkhan92_hackathon-ai-sarawak-activity-7502243111935307776-MYar?utm_source=share&utm_medium=member_desktop&rcm=ACoAABzB85UB8iZMlY6hoj9K3g7MfcRKsCZOvqw https://www.linkedin.com/posts/sohwanwei_saiyan-saiyanbuilders-singaporesarawak-ugcPost-7502187273908596737-4La9?utm_source=share&utm_medium=member_desktop&rcm=ACoAABzB85UB8iZMlY6hoj9K3g7MfcRKsCZOvqw | C82: https://www.instagram.com/p/Dc5QhzbmxIE/?utm_source=ig_web_copy_link&stkn=MzRlODBiNWFlZA== https://www.instagram.com/reel/Dc5TWF8TcSt/?utm_source=ig_web_copy_link&stkn=MzRlODBiNWFlZA== https://www.instagram.com/reel/Dc5ksn1xwM_/?utm_source=ig_web_copy_link&stkn=MzRlODBiNWFlZA== https://www.instagram.com/p/Dc7j6K9k9Rn/?utm_source=ig_web_copy_link&stkn=MzRlODBiNWFlZA== https://www.instagram.com/p/DdEa6eRHUJq/?utm_source=ig_web_copy_link&stkn=MzRlODBiNWFlZA== https://www.instagram.com/reel/Dc8Mz_8z325/ https://www.instagram.com/reel/Dc5UiWhxVXR/
A83: #080 | B83: https://www.linkedin.com/posts/sayyidkhan92_hackathon-astra-ai-activity-7506342725504557056-ifQj?utm_source=share&utm_medium=member_desktop&rcm=ACoAABzB85UB8iZMlY6hoj9K3g7MfcRKsCZOvqw https://www.linkedin.com/posts/sayyidkhan92_hackathon-astra-ai-activity-7504873783019597824-0MLK?utm_source=share&utm_medium=member_desktop&rcm=ACoAABzB85UB8iZMlY6hoj9K3g7MfcRKsCZOvqw https://www.linkedin.com/feed/update/urn:li:activity:7505062754270175232/ | C83: https://www.instagram.com/reel/DdOiYzlxNim/?utm_source=ig_web_copy_link&stkn=MzRlODBiNWFlZA== https://www.instagram.com/p/DdY81t8k9G8/?utm_source=ig_web_copy_link&stkn=MzRlODBiNWFlZA==
A84: #081 | C84: https://www.instagram.com/p/Dddoi71EyhB/?utm_source=ig_web_copy_link&stkn=MzRlODBiNWFlZA==

Sheet Theme Map
A1: Theme category map
A2: Keep detailed themes in the Hackathons sheet. Update this map to control the general-category dashboard; unmapped themes appear as Unclassified.
A4: Raw Theme | B4: General Category | C4: Notes
A5: Advertising | B5: Consumer & Lifestyle
A6: Afterlife | B6: Creative & Play
A7: Agentic AI | B7: AI & Data
A8: Agentic AI (Voice) | B8: AI & Data
A9: Blockchain | B9: Emerging Tech
A10: Curated Theme: Touch Grass | B10: Open / Experimental | C10: Event-specific prompt
A11: Data Analytics | B11: AI & Data
A12: Delivery | B12: Operations & Productivity
A13: Design | B13: Creative & Play
A14: E-Waste | B14: Sustainability & Civic
A15: Edu-Fintech | B15: Finance & Commerce
A16: Education | B16: Education & Workforce
A17: Education / Linguistics | B17: Education & Workforce
A18: Events | B18: Operations & Productivity
A19: Family | B19: Consumer & Lifestyle
A20: Family Office | B20: Finance & Commerce
A21: Financial Legacy | B21: Finance & Commerce
A22: Fintech | B22: Finance & Commerce
... A26: Game | B26: Creative & Play
A27: Google | B27: Open / Experimental | C27: Platform or event context; reclassify if needed
A28: Health | B28: Health & Wellbeing
A29: Healthcare | B29: Health & Wellbeing
A30: Healthy Living | B30: Health & Wellbeing
A31: Human Resource | B31: Education & Workforce
A32: Infra | B32: Operations & Productivity
A33: Logistics | B33: Operations & Productivity
A34: ML Inference | B34: AI & Data
A35: Movie | B35: Creative & Play
A36: Open Track | B36: Open / Experimental | C36: Event-specific prompt
A37: Personal Development | B37: Education & Workforce
A38: Pest Busting | B38: Sustainability & Civic
A39: Productivity | B39: Operations & Productivity | C39: Case-insensitive match also covers lower-case values
A40: Project Management | B40: Operations & Productivity
A41: Property Management | B41: Operations & Productivity
A42: Shariah Compliance | B42: Finance & Commerce
A43: Silly Solutions | B43: Open / Experimental | C43: Event-specific prompt
A44: Smart Nation | B44: Sustainability & Civic
A45: Smart Nation / Social Good | B45: Sustainability & Civic
A46: Social Enterprise | B46: Sustainability & Civic
A47: Space | B47: Emerging Tech
A48: Various | B48: Open / Experimental | C48: Mixed or unspecified
A49: Virtual Reality | B49: Emerging Tech
A50: Waste Management / Sustainability | B50: Sustainability & Civic
A51: Weather | B51: Sustainability & Civic
A52: Wellness / Healthcare | B52: Health & Wellbeing
A53: Embedded Models | B53: Agentic AI | C53: On-device and local model builds
A54: Build for Someone Else | B54: Open / Experimental
A55: ChatGPT Sites | B55: AI & Data | C55: ChatGPT and Codex site builds
A56: GPT-6 Astra | B56: AI & Data | C56: GPT-6 Astra hackathon builds
A57: Micro Business | B57: Finance & Commerce | C57: Small-business digital experiences and commerce tools
A58: Anti Drugs | B58: Smart Nation / Social Good | C58: Interactive anti-drug and youth-wellbeing builds

Sheet Prize Money
A1: Prize Money & Rewards
A2: Live summary from the structured award fields on the Hackathons tab. Values refresh when you update the highlighted classification columns there.
A4: Cash-equivalent prizes | H4: Credits and subscriptions
A5: SGD cash + vouchers | C5: =SUMIFS('Prize Details'!$H$5:$H$28,'Prize Details'!$I$5:$I$28,"SGD",'Prize Details'!$X$5:$X$28,"Yes") -> 2850 | H5: USD credits | J5: =SUMIFS('Prize Details'!$K$5:$K$28,'Prize Details'!$L$5:$L$28,"USD") -> 131400
A6: USD cash + vouchers | C6: =SUMIFS('Prize Details'!$H$5:$H$28,'Prize Details'!$I$5:$I$28,"USD",'Prize Details'!$X$5:$X$28,"Yes") -> 0 | H6: SGD credits | J6: =SUMIFS('Prize Details'!$K$5:$K$28,'Prize Details'!$L$5:$L$28,"SGD") -> 385
A7: Confirmed prize records | C7: =COUNTIFS('Prize Details'!$H$5:$H$28,">0",'Prize Details'!$X$5:$X$28,"Yes") -> 6 | H7: Subscription value (USD) | J7: =SUMIFS('Prize Details'!$O$5:$O$28,'Prize Details'!$P$5:$P$28,"USD") -> 156
A8: Includes vouchers you chose to treat as cash-equivalent. Funding is shown separately and included in the all-tracked totals below. | H8: Subscriptions collected | J8: =SUM('Prize Details'!$N$5:$N$28) -> 4
A10: Breakdown by currency
A11: Category | B11: Currency | C11: Team total | D11: Individual total | E11: How it is calculated | H11: Assets Collected
A12: Cash-equivalent prizes | B12: SGD | C12: =SUMIFS('Prize Details'!$H$5:$H$28,'Prize Details'!$I$5:$I$28,B12,'Prize Details'!$X$5:$X$28,"Yes") -> 2850 | D12: =SUMIFS('Prize Details'!$J$5:$J$28,'Prize Details'!$I$5:$I$28,B12,'Prize Details'!$X$5:$X$28,"Yes") -> 1058.3333 | E12: Cash and vouchers marked Yes | H12: Recorded asset entries | J12: =COUNTIFS(Hackathons!$AA$2:$AA$82,"<>") -> 4
A13: Cash-equivalent prizes | B13: USD | C13: =SUMIFS('Prize Details'!$H$5:$H$28,'Prize Details'!$I$5:$I$28,B13,'Prize Details'!$X$5:$X$28,"Yes") -> 0 | D13: =SUMIFS('Prize Details'!$J$5:$J$28,'Prize Details'!$I$5:$I$28,B13,'Prize Details'!$X$5:$X$28,"Yes") -> 0 | E13: Cash and vouchers marked Yes | H13: Trophies collected | J13: =SUM(Hackathons!$AB$2:$AB$82) -> 2
A14: Credits | B14: USD | C14: =SUMIFS('Prize Details'!$K$5:$K$28,'Prize Details'!$L$5:$L$28,B14) -> 131400 | D14: =SUMIFS('Prize Details'!$M$5:$M$28,'Prize Details'!$L$5:$L$28,B14) -> 41558.333 | E14: Non-cash product / API credits | H14: Hackathon | I14: Item | J14: Trophies
A15: Credits | B15: SGD | C15: =SUMIFS('Prize Details'!$K$5:$K$28,'Prize Details'!$L$5:$L$28,B15) -> 385 | D15: =SUMIFS('Prize Details'!$M$5:$M$28,'Prize Details'!$L$5:$L$28,B15) -> 385 | E15: Non-cash product / API credits | H15: =Hackathons!B5 -> Fintech Festival Hackathon 2016 | I15: =Hackathons!AA5 -> SmartWatch | J15: =IF(Hackathons!AB5="","",Hackathons!AB5) -> 0
A16: Subscriptions | B16: USD | C16: =SUMIFS('Prize Details'!$O$5:$O$28,'Prize Details'!$P$5:$P$28,B16) -> 156 | D16: =SUMIFS('Prize Details'!$Q$5:$Q$28,'Prize Details'!$P$5:$P$28,B16) -> 39 | E16: Known subscription value | H16: =Hackathons!B41 -> Sarawak AI Hackathon 2025 | I16: =Hackathons!AA41 -> Trophy | J16: =IF(Hackathons!AB41="","",Hackathons!AB41) -> 1
A17: Funding | B17: SGD | C17: =SUMIFS('Prize Details'!$R$5:$R$28,'Prize Details'!$S$5:$S$28,B17) -> 18000 | D17: =SUMIFS('Prize Details'!$T$5:$T$28,'Prize Details'!$S$5:$S$28,B17) -> 3600 | E17: Seed funding / grants | H17: =Hackathons!B62 -> Vercel Zero to Agent: Singapore (1 Hr Hackathon) 2026 | I17: =Hackathons!AA62 -> v0 Sock | J17: =IF(Hackathons!AB62="","",Hackathons!AB62) -> 0
H18: =Hackathons!B80 -> SG × SWK Friendship AI Business Design Hackathon | I18: =Hackathons!AA80 -> Trophy | J18: =IF(Hackathons!AB80="","",Hackathons!AB80) -> 1
H19: Assets remain outside monetary totals until a value is recorded.
A20: All tracked monetary value | B20: Currency | C20: Amount | D20: Includes | H20: Individual Total (Your Share)
A21: All prize value | B21: SGD | C21: =SUMIFS('Prize Details'!$H$5:$H$28,'Prize Details'!$I$5:$I$28,B21,'Prize Details'!$X$5:$X$28,"Yes")+SUMIFS('Prize Details'!$K$5:$K$28,'Prize Details'!$L$5:$L$28,B21)+SUMIFS('Prize Details'!$O$5:$O$28,'Prize Details'!$P$5:$P$28,B21)+SUMIFS('Prize Details'!$R$5:$R$28,'Prize Details'!$S$5:$S$28,B21) -> 21235 | D21: Cash, credits, subscriptions, funding | H21: Individual tracked value | J21: SGD | K21: =SUMIFS('Prize Details'!$J$5:$J$28,'Prize Details'!$I$5:$I$28,J21)+SUMIFS('Prize Details'!$M$5:$M$28,'Prize Details'!$L$5:$L$28,J21)+SUMIFS('Prize Details'!$Q$5:$Q$28,'Prize Details'!$P$5:$P$28,J21)+SUMIFS('Prize Details'!$T$5:$T$28,'Prize Details'!$S$5:$S$28,J21) -> 5043.3333
A22: All prize value | B22: USD | C22: =SUMIFS('Prize Details'!$H$5:$H$28,'Prize Details'!$I$5:$I$28,B22,'Prize Details'!$X$5:$X$28,"Yes")+SUMIFS('Prize Details'!$K$5:$K$28,'Prize Details'!$L$5:$L$28,B22)+SUMIFS('Prize Details'!$O$5:$O$28,'Prize Details'!$P$5:$P$28,B22)+SUMIFS('Prize Details'!$R$5:$R$28,'Prize Details'!$S$5:$S$28,B22) -> 131556 | D22: Cash, credits, subscriptions, funding | J22: USD | K22: =SUMIFS('Prize Details'!$J$5:$J$28,'Prize Details'!$I$5:$I$28,J22)+SUMIFS('Prize Details'!$M$5:$M$28,'Prize Details'!$L$5:$L$28,J22)+SUMIFS('Prize Details'!$Q$5:$Q$28,'Prize Details'!$P$5:$P$28,J22)+SUMIFS('Prize Details'!$T$5:$T$28,'Prize Details'!$S$5:$S$28,J22) -> 41597.333
A23: This combines money-like prizes, credits, subscriptions, and funding in the same currency. Trophies and physical assets are excluded because they have no recorded monetary value.
A25: Update the yellow structured fields in Hackathons; this dashboard refreshes automatically.

Sheet Prize Details
A1: Prize Details — Team Totals and Individual Share
A2: Team totals reflect the allocation basis. Per Team Member awards multiply the per-person award by the hackathon team count; individual values retain the per-person amount.
A3: Records tracked | D3: =COUNTA(A5:A28) -> 24 | F3: Cash-equivalent total (SGD) | I3: =SUMIFS(Hackathons!$S$2:$S$82,Hackathons!$T$2:$T$82,"SGD",Hackathons!$AE$2:$AE$82,"Yes") -> 2750 | L3: Cash-equivalent total (USD) | O3: =SUMIFS(Hackathons!$S$2:$S$82,Hackathons!$T$2:$T$82,"USD",Hackathons!$AE$2:$AE$82,"Yes") -> 0
A4: # | B4: Hackathon | C4: Award Summary | D4: Award Type | E4: Additional Info | F4: Hackathon Team Members | G4: Prize Allocation | H4: Team Cash | I4: Cash Currency | J4: Individual Cash | K4: Team Credits | L4: Credit Currency / Units | M4: Individual Credits | N4: Team Subscription Count | O4: Team Subscription Value | P4: Subscription Currency | Q4: Individual Subscription Value | R4: Team Funding | S4: Funding Currency | T4: Individual Funding | U4: Other Non-cash Prize | V4: Physical Asset | W4: Trophy Count | X4: Money Counted? | Y4: Review Note
A5: =Hackathons!A2 -> 1 | B5: =Hackathons!B2 -> Education Technology Hackathon | C5: =Hackathons!AG2 -> 1st Place — S$18,000 Seed Funding | D5: =IF(Hackathons!Q2="","",Hackathons!Q2) -> 1st Place | E5: =IF(Hackathons!R2="","",Hackathons!R2) | F5: =IF(Hackathons!AH2="","",Hackathons!AH2) -> 5 | G5: =IF(Hackathons!AI2="","",Hackathons!AI2) -> Per Team | H5: =IF(Hackathons!S2="","",IF(G5="Per Team Member",Hackathons!S2*F5,Hackathons!S2)) | I5: =IF(Hackathons!T2="","",Hackathons!T2) | J5: =IF(OR(H5="",F5=""),"",H5/F5) | K5: =IF(Hackathons!U2="","",IF(G5="Per Team Member",Hackathons!U2*F5,Hackathons!U2)) | L5: =IF(Hackathons!V2="","",Hackathons!V2) | M5: =IF(OR(K5="",F5=""),"",K5/F5) | N5: =IF(Hackathons!W2="","",IF(G5="Per Team Member",Hackathons!W2*F5,Hackathons!W2)) | O5: =IF(Hackathons!X2="","",IF(G5="Per Team Member",Hackathons!X2*F5,Hackathons!X2)) | P5: =IF(Hackathons!Y2="","",Hackathons!Y2) | Q5: =IF(OR(O5="",F5=""),"",O5/F5) | R5: =IF(Hackathons!AC2="","",IF(G5="Per Team Member",Hackathons!AC2*F5,Hackathons!AC2)) -> 18000 | S5: =IF(Hackathons!AD2="","",Hackathons!AD2) -> SGD | T5: =IF(OR(R5="",F5="",F5=0),"",R5/F5) -> 3600 | U5: =IF(Hackathons!Z2="","",Hackathons!Z2) | V5: =IF(Hackathons!AA2="","",Hackathons!AA2) | W5: =IF(Hackathons!AB2="","",Hackathons!AB2) | X5: =IF(Hackathons!AE2="","",Hackathons!AE2) -> Exclude | Y5: =IF(Hackathons!AF2="","",Hackathons!AF2) -> Funding, not a cash prize
A6: =Hackathons!A4 -> 3 | B6: =Hackathons!B4 -> DataDriven Hackathon 2016 | C6: =Hackathons!AG4 -> Best Project | D6: =IF(Hackathons!Q4="","",Hackathons!Q4) -> Best Project | E6: =IF(Hackathons!R4="","",Hackathons!R4) -> Rated best project | F6: =IF(Hackathons!AH4="","",Hackathons!AH4) -> 6 | G6: =IF(Hackathons!AI4="","",Hackathons!AI4) -> Per Team | H6: =IF(Hackathons!S4="","",IF(G6="Per Team Member",Hackathons!S4*F6,Hackathons!S4)) | I6: =IF(Hackathons!T4="","",Hackathons!T4) | J6: =IF(OR(H6="",F6=""),"",H6/F6) | K6: =IF(Hackathons!U4="","",IF(G6="Per Team Member",Hackathons!U4*F6,Hackathons!U4)) | L6: =IF(Hackathons!V4="","",Hackathons!V4) | M6: =IF(OR(K6="",F6=""),"",K6/F6) | N6: =IF(Hackathons!W4="","",IF(G6="Per Team Member",Hackathons!W4*F6,Hackathons!W4)) | O6: =IF(Hackathons!X4="","",IF(G6="Per Team Member",Hackathons!X4*F6,Hackathons!X4)) | P6: =IF(Hackathons!Y4="","",Hackathons!Y4) | Q6: =IF(OR(O6="",F6=""),"",O6/F6) | R6: =IF(Hackathons!AC4="","",IF(G6="Per Team Member",Hackathons!AC4*F6,Hackathons!AC4)) | S6: =IF(Hackathons!AD4="","",Hackathons!AD4) | T6: =IF(OR(R6="",F6="",F6=0),"",R6/F6) | U6: =IF(Hackathons!Z4="","",Hackathons!Z4) | V6: =IF(Hackathons!AA4="","",Hackathons!AA4) | W6: =IF(Hackathons!AB4="","",Hackathons!AB4) | X6: =IF(Hackathons!AE4="","",Hackathons!AE4) -> Exclude | Y6: =IF(Hackathons!AF4="","",Hackathons!AF4) -> Recognition only
A7: =Hackathons!A5 -> 4 | B7: =Hackathons!B5 -> Fintech Festival Hackathon 2016 | C7: =Hackathons!AG5 -> 1st Place — Best Use of IBM Bluemix — US$100,000 IBM Bluemix Credits — SmartWatch | D7: =IF(Hackathons!Q5="","",Hackathons!Q5) -> 1st Place | E7: =IF(Hackathons!R5="","",Hackathons!R5) -> Best Use of IBM Bluemix | F7: =IF(Hackathons!AH5="","",Hackathons!AH5) -> 4 | G7: =IF(Hackathons!AI5="","",Hackathons!AI5) -> Per Team | H7: =IF(Hackathons!S5="","",IF(G7="Per Team Member",Hackathons!S5*F7,Hackathons!S5)) | I7: =IF(Hackathons!T5="","",Hackathons!T5) | J7: =IF(OR(H7="",F7=""),"",H7/F7) | K7: =IF(Hackathons!U5="","",IF(G7="Per Team Member",Hackathons!U5*F7,Hackathons!U5)) -> 100000 | L7: =IF(Hackathons!V5="","",Hackathons!V5) -> USD | M7: =IF(OR(K7="",F7=""),"",K7/F7) -> 25000 | N7: =IF(Hackathons!W5="","",IF(G7="Per Team Member",Hackathons!W5*F7,Hackathons!W5)) | O7: =IF(Hackathons!X5="","",IF(G7="Per Team Member",Hackathons!X5*F7,Hackathons!X5)) | P7: =IF(Hackathons!Y5="","",Hackathons!Y5) | Q7: =IF(OR(O7="",F7=""),"",O7/F7) | R7: =IF(Hackathons!AC5="","",IF(G7="Per Team Member",Hackathons!AC5*F7,Hackathons!AC5)) | S7: =IF(Hackathons!AD5="","",Hackathons!AD5) | T7: =IF(OR(R7="",F7="",F7=0),"",R7/F7) | U7: =IF(Hackathons!Z5="","",Hackathons!Z5) -> IBM Bluemix credits; SmartWatch | V7: =IF(Hackathons!AA5="","",Hackathons!AA5) -> SmartWatch | W7: =IF(Hackathons!AB5="","",Hackathons!AB5) -> 0 | X7: =IF(Hackathons!AE5="","",Hackathons!AE5) -> Exclude | Y7: =IF(Hackathons!AF5="","",Hackathons!AF5) -> US$100,000 IBM Bluemix credit value
A8: =Hackathons!A11 -> 10 | B8: =Hackathons!B11 -> DataDriven Hackathon 2017 | C8: =Hackathons!AG11 -> Best Project | D8: =IF(Hackathons!Q11="","",Hackathons!Q11) -> Best Project | E8: =IF(Hackathons!R11="","",Hackathons!R11) -> Rated best project | F8: =IF(Hackathons!AH11="","",Hackathons!AH11) -> 3 | G8: =IF(Hackathons!AI11="","",Hackathons!AI11) -> Per Team | H8: =IF(Hackathons!S11="","",IF(G8="Per Team Member",Hackathons!S11*F8,Hackathons!S11)) | I8: =IF(Hackathons!T11="","",Hackathons!T11) | J8: =IF(OR(H8="",F8=""),"",H8/F8) | K8: =IF(Hackathons!U11="","",IF(G8="Per Team Member",Hackathons!U11*F8,Hackathons!U11)) | L8: =IF(Hackathons!V11="","",Hackathons!V11) | M8: =IF(OR(K8="",F8=""),"",K8/F8) | N8: =IF(Hackathons!W11="","",IF(G8="Per Team Member",Hackathons!W11*F8,Hackathons!W11)) | O8: =IF(Hackathons!X11="","",IF(G8="Per Team Member",Hackathons!X11*F8,Hackathons!X11)) | P8: =IF(Hackathons!Y11="","",Hackathons!Y11) | Q8: =IF(OR(O8="",F8=""),"",O8/F8) | R8: =IF(Hackathons!AC11="","",IF(G8="Per Team Member",Hackathons!AC11*F8,Hackathons!AC11)) | S8: =IF(Hackathons!AD11="","",Hackathons!AD11) | T8: =IF(OR(R8="",F8="",F8=0),"",R8/F8) | U8: =IF(Hackathons!Z11="","",Hackathons!Z11) | V8: =IF(Hackathons!AA11="","",Hackathons!AA11) | W8: =IF(Hackathons!AB11="","",Hackathons!AB11) | X8: =IF(Hackathons!AE11="","",Hackathons!AE11) -> Exclude | Y8: =IF(Hackathons!AF11="","",Hackathons!AF11) -> Recognition only
A9: =Hackathons!A15 -> 14 | B9: =Hackathons!B15 -> #SPSEC SP Hackathon 2018 | C9: =Hackathons!AG15 -> 3rd Place — S$100 Capitaland Voucher Each | D9: =IF(Hackathons!Q15="","",Hackathons!Q15) -> 3rd Place | E9: =IF(Hackathons!R15="","",Hackathons!R15) | F9: =IF(Hackathons!AH15="","",Hackathons!AH15) -> 2 | G9: =IF(Hackathons!AI15="","",Hackathons!AI15) -> Per Team Member | H9: =IF(Hackathons!S15="","",IF(G9="Per Team Member",Hackathons!S15*F9,Hackathons!S15)) -> 200 | I9: =IF(Hackathons!T15="","",Hackathons!T15) -> SGD | J9: =IF(OR(H9="",F9=""),"",H9/F9) -> 100 | K9: =IF(Hackathons!U15="","",IF(G9="Per Team Member",Hackathons!U15*F9,Hackathons!U15)) | L9: =IF(Hackathons!V15="","",Hackathons!V15) | M9: =IF(OR(K9="",F9=""),"",K9/F9) | N9: =IF(Hackathons!W15="","",IF(G9="Per Team Member",Hackathons!W15*F9,Hackathons!W15)) | O9: =IF(Hackathons!X15="","",IF(G9="Per Team Member",Hackathons!X15*F9,Hackathons!X15)) | P9: =IF(Hackathons!Y15="","",Hackathons!Y15) | Q9: =IF(OR(O9="",F9=""),"",O9/F9) | R9: =IF(Hackathons!AC15="","",IF(G9="Per Team Member",Hackathons!AC15*F9,Hackathons!AC15)) | S9: =IF(Hackathons!AD15="","",Hackathons!AD15) | T9: =IF(OR(R9="",F9="",F9=0),"",R9/F9) | U9: =IF(Hackathons!Z15="","",Hackathons!Z15) -> S$100 Capitaland voucher | V9: =IF(Hackathons!AA15="","",Hackathons!AA15) | W9: =IF(Hackathons!AB15="","",Hackathons!AB15) | X9: =IF(Hackathons!AE15="","",Hackathons!AE15) -> Yes | Y9: =IF(Hackathons!AF15="","",Hackathons!AF15) -> Voucher counted as cash equivalent
A10: =Hackathons!A18 -> 17 | B10: =Hackathons!B18 -> #Mosque-Tech Challenge 2018 | C10: =Hackathons!AG18 -> 2nd Place — S$600 Cash | D10: =IF(Hackathons!Q18="","",Hackathons!Q18) -> 2nd Place | E10: =IF(Hackathons!R18="","",Hackathons!R18) | F10: =IF(Hackathons!AH18="","",Hackathons!AH18) -> 3 | G10: =IF(Hackathons!AI18="","",Hackathons!AI18) -> Per Team | H10: =IF(Hackathons!S18="","",IF(G10="Per Team Member",Hackathons!S18*F10,Hackathons!S18)) -> 600 | I10: =IF(Hackathons!T18="","",Hackathons!T18) -> SGD | J10: =IF(OR(H10="",F10=""),"",H10/F10) -> 200 | K10: =IF(Hackathons!U18="","",IF(G10="Per Team Member",Hackathons!U18*F10,Hackathons!U18)) | L10: =IF(Hackathons!V18="","",Hackathons!V18) | M10: =IF(OR(K10="",F10=""),"",K10/F10) | N10: =IF(Hackathons!W18="","",IF(G10="Per Team Member",Hackathons!W18*F10,Hackathons!W18)) | O10: =IF(Hackathons!X18="","",IF(G10="Per Team Member",Hackathons!X18*F10,Hackathons!X18)) | P10: =IF(Hackathons!Y18="","",Hackathons!Y18) | Q10: =IF(OR(O10="",F10=""),"",O10/F10) | R10: =IF(Hackathons!AC18="","",IF(G10="Per Team Member",Hackathons!AC18*F10,Hackathons!AC18)) | S10: =IF(Hackathons!AD18="","",Hackathons!AD18) | T10: =IF(OR(R10="",F10="",F10=0),"",R10/F10) | U10: =IF(Hackathons!Z18="","",Hackathons!Z18) | V10: =IF(Hackathons!AA18="","",Hackathons!AA18) | W10: =IF(Hackathons!AB18="","",Hackathons!AB18) | X10: =IF(Hackathons!AE18="","",Hackathons!AE18) -> Yes | Y10: =IF(Hackathons!AF18="","",Hackathons!AF18) -> Explicit cash
A11: =Hackathons!A26 -> 25 | B11: =Hackathons!B26 -> #Mosque Hackathon 2019 | C11: =Hackathons!AG26 -> 3rd Place — S$500 Cash | D11: =IF(Hackathons!Q26="","",Hackathons!Q26) -> 3rd Place | E11: =IF(Hackathons!R26="","",Hackathons!R26) | F11: =IF(Hackathons!AH26="","",Hackathons!AH26) -> 6 | G11: =IF(Hackathons!AI26="","",Hackathons!AI26) -> Per Team | H11: =IF(Hackathons!S26="","",IF(G11="Per Team Member",Hackathons!S26*F11,Hackathons!S26)) -> 500 | I11: =IF(Hackathons!T26="","",Hackathons!T26) -> SGD | J11: =IF(OR(H11="",F11=""),"",H11/F11) -> 83.333333 | K11: =IF(Hackathons!U26="","",IF(G11="Per Team Member",Hackathons!U26*F11,Hackathons!U26)) | L11: =IF(Hackathons!V26="","",Hackathons!V26) | M11: =IF(OR(K11="",F11=""),"",K11/F11) | N11: =IF(Hackathons!W26="","",IF(G11="Per Team Member",Hackathons!W26*F11,Hackathons!W26)) | O11: =IF(Hackathons!X26="","",IF(G11="Per Team Member",Hackathons!X26*F11,Hackathons!X26)) | P11: =IF(Hackathons!Y26="","",Hackathons!Y26) | Q11: =IF(OR(O11="",F11=""),"",O11/F11) | R11: =IF(Hackathons!AC26="","",IF(G11="Per Team Member",Hackathons!AC26*F11,Hackathons!AC26)) | S11: =IF(Hackathons!AD26="","",Hackathons!AD26) | T11: =IF(OR(R11="",F11="",F11=0),"",R11/F11) | U11: =IF(Hackathons!Z26="","",Hackathons!Z26) | V11: =IF(Hackathons!AA26="","",Hackathons!AA26) | W11: =IF(Hackathons!AB26="","",Hackathons!AB26) | X11: =IF(Hackathons!AE26="","",Hackathons!AE26) -> Yes | Y11: =IF(Hackathons!AF26="","",Hackathons!AF26) -> Explicit cash
A12: =Hackathons!A34 -> 33 | B12: =Hackathons!B34 -> ICP Ideathon 2023 | C12: =Hackathons!AG34 -> 3rd Place — S$250 Cash | D12: =IF(Hackathons!Q34="","",Hackathons!Q34) -> 3rd Place | E12: =IF(Hackathons!R34="","",Hackathons!R34) | F12: =IF(Hackathons!AH34="","",Hackathons!AH34) -> 2 | G12: =IF(Hackathons!AI34="","",Hackathons!AI34) -> Per Team | H12: =IF(Hackathons!S34="","",IF(G12="Per Team Member",Hackathons!S34*F12,Hackathons!S34)) -> 250 | I12: =IF(Hackathons!T34="","",Hackathons!T34) -> SGD | J12: =IF(OR(H12="",F12=""),"",H12/F12) -> 125 | K12: =IF(Hackathons!U34="","",IF(G12="Per Team Member",Hackathons!U34*F12,Hackathons!U34)) | L12: =IF(Hackathons!V34="","",Hackathons!V34) | M12: =IF(OR(K12="",F12=""),"",K12/F12) | N12: =IF(Hackathons!W34="","",IF(G12="Per Team Member",Hackathons!W34*F12,Hackathons!W34)) | O12: =IF(Hackathons!X34="","",IF(G12="Per Team Member",Hackathons!X34*F12,Hackathons!X34)) | P12: =IF(Hackathons!Y34="","",Hackathons!Y34) | Q12: =IF(OR(O12="",F12=""),"",O12/F12) | R12: =IF(Hackathons!AC34="","",IF(G12="Per Team Member",Hackathons!AC34*F12,Hackathons!AC34)) | S12: =IF(Hackathons!AD34="","",Hackathons!AD34) | T12: =IF(OR(R12="",F12="",F12=0),"",R12/F12) | U12: =IF(Hackathons!Z34="","",Hackathons!Z34) | V12: =IF(Hackathons!AA34="","",Hackathons!AA34) | W12: =IF(Hackathons!AB34="","",Hackathons!AB34) | X12: =IF(Hackathons!AE34="","",Hackathons!AE34) -> Yes | Y12: =IF(Hackathons!AF34="","",Hackathons!AF34) -> Confirmed cash
A13: =Hackathons!A36 -> 35 | B13: =Hackathons!B36 -> Mosque Tech Challenge 2025 | C13: =Hackathons!AG36 -> 2nd Place — S$1,000 Cash | D13: =IF(Hackathons!Q36="","",Hackathons!Q36) -> 2nd Place | E13: =IF(Hackathons!R36="","",Hackathons!R36) | F13: =IF(Hackathons!AH36="","",Hackathons!AH36) -> 4 | G13: =IF(Hackathons!AI36="","",Hackathons!AI36) -> Per Team | H13: =IF(Hackathons!S36="","",IF(G13="Per Team Member",Hackathons!S36*F13,Hackathons!S36)) -> 1000 | I13: =IF(Hackathons!T36="","",Hackathons!T36) -> SGD | J13: =IF(OR(H13="",F13=""),"",H13/F13) -> 250 | K13: =IF(Hackathons!U36="","",IF(G13="Per Team Member",Hackathons!U36*F13,Hackathons!U36)) | L13: =IF(Hackathons!V36="","",Hackathons!V36) | M13: =IF(OR(K13="",F13=""),"",K13/F13) | N13: =IF(Hackathons!W36="","",IF(G13="Per Team Member",Hackathons!W36*F13,Hackathons!W36)) | O13: =IF(Hackathons!X36="","",IF(G13="Per Team Member",Hackathons!X36*F13,Hackathons!X36)) | P13: =IF(Hackathons!Y36="","",Hackathons!Y36) | Q13: =IF(OR(O13="",F13=""),"",O13/F13) | R13: =IF(Hackathons!AC36="","",IF(G13="Per Team Member",Hackathons!AC36*F13,Hackathons!AC36)) | S13: =IF(Hackathons!AD36="","",Hackathons!AD36) | T13: =IF(OR(R13="",F13="",F13=0),"",R13/F13) | U13: =IF(Hackathons!Z36="","",Hackathons!Z36) | V13: =IF(Hackathons!AA36="","",Hackathons!AA36) | W13: =IF(Hackathons!AB36="","",Hackathons!AB36) | X13: =IF(Hackathons!AE36="","",Hackathons!AE36) -> Yes | Y13: =IF(Hackathons!AF36="","",Hackathons!AF36) -> Confirmed cash
A14: =Hackathons!A39 -> 38 | B14: =Hackathons!B39 -> OOJU X Manus.AI Hackathon 2025 | C14: =Hackathons!AG39 -> 2nd Place — Manus Pro Subscription (US$39/month each) | D14: =IF(Hackathons!Q39="","",Hackathons!Q39) -> 2nd Prize | E14: =IF(Hackathons!R39="","",Hackathons!R39) | F14: =IF(Hackathons!AH39="","",Hackathons!AH39) -> 4 | G14: =IF(Hackathons!AI39="","",Hackathons!AI39) -> Per Team Member | H14: =IF(Hackathons!S39="","",IF(G14="Per Team Member",Hackathons!S39*F14,Hackathons!S39)) | I14: =IF(Hackathons!T39="","",Hackathons!T39) | J14: =IF(OR(H14="",F14=""),"",H14/F14) | K14: =IF(Hackathons!U39="","",IF(G14="Per Team Member",Hackathons!U39*F14,Hackathons!U39)) | L14: =IF(Hackathons!V39="","",Hackathons!V39) | M14: =IF(OR(K14="",F14=""),"",K14/F14) | N14: =IF(Hackathons!W39="","",IF(G14="Per Team Member",Hackathons!W39*F14,Hackathons!W39)) -> 4 | O14: =IF(Hackathons!X39="","",IF(G14="Per Team Member",Hackathons!X39*F14,Hackathons!X39)) -> 156 | P14: =IF(Hackathons!Y39="","",Hackathons!Y39) -> USD | Q14: =IF(OR(O14="",F14=""),"",O14/F14) -> 39 | R14: =IF(Hackathons!AC39="","",IF(G14="Per Team Member",Hackathons!AC39*F14,Hackathons!AC39)) | S14: =IF(Hackathons!AD39="","",Hackathons!AD39) | T14: =IF(OR(R14="",F14="",F14=0),"",R14/F14) | U14: =IF(Hackathons!Z39="","",Hackathons!Z39) -> Manus Pro subscription | V14: =IF(Hackathons!AA39="","",Hackathons!AA39) | W14: =IF(Hackathons!AB39="","",Hackathons!AB39) | X14: =IF(Hackathons!AE39="","",Hackathons!AE39) -> Exclude | Y14: =IF(Hackathons!AF39="","",Hackathons!AF39) -> US$39 monthly value at award period
A15: =Hackathons!A41 -> 40 | B15: =Hackathons!B41 -> Sarawak AI Hackathon 2025 | C15: =Hackathons!AG41 -> Novel Hackathon Finisher — Trophy | D15: =IF(Hackathons!Q41="","",Hackathons!Q41) -> Novel Hackathon Finisher | E15: =IF(Hackathons!R41="","",Hackathons!R41) | F15: =IF(Hackathons!AH41="","",Hackathons!AH41) -> 2 | G15: =IF(Hackathons!AI41="","",Hackathons!AI41) -> Per Team | H15: =IF(Hackathons!S41="","",IF(G15="Per Team Member",Hackathons!S41*F15,Hackathons!S41)) | I15: =IF(Hackathons!T41="","",Hackathons!T41) | J15: =IF(OR(H15="",F15=""),"",H15/F15) | K15: =IF(Hackathons!U41="","",IF(G15="Per Team Member",Hackathons!U41*F15,Hackathons!U41)) | L15: =IF(Hackathons!V41="","",Hackathons!V41) | M15: =IF(OR(K15="",F15=""),"",K15/F15) | N15: =IF(Hackathons!W41="","",IF(G15="Per Team Member",Hackathons!W41*F15,Hackathons!W41)) | O15: =IF(Hackathons!X41="","",IF(G15="Per Team Member",Hackathons!X41*F15,Hackathons!X41)) | P15: =IF(Hackathons!Y41="","",Hackathons!Y41) | Q15: =IF(OR(O15="",F15=""),"",O15/F15) | R15: =IF(Hackathons!AC41="","",IF(G15="Per Team Member",Hackathons!AC41*F15,Hackathons!AC41)) | S15: =IF(Hackathons!AD41="","",Hackathons!AD41) | T15: =IF(OR(R15="",F15="",F15=0),"",R15/F15) | U15: =IF(Hackathons!Z41="","",Hackathons!Z41) -> Trophy | V15: =IF(Hackathons!AA41="","",Hackathons!AA41) -> Trophy | W15: =IF(Hackathons!AB41="","",Hackathons!AB41) -> 1 | X15: =IF(Hackathons!AE41="","",Hackathons!AE41) -> Exclude | Y15: =IF(Hackathons!AF41="","",Hackathons!AF41) -> Trophy, not cash
A16: =Hackathons!A43 -> 42 | B16: =Hackathons!B43 -> Nosana Hackathon 2025 | C16: =Hackathons!AG43 -> 1st Place — US$500 Nosana Cloud Credits | D16: =IF(Hackathons!Q43="","",Hackathons!Q43) -> 1st Prize | E16: =IF(Hackathons!R43="","",Hackathons!R43) | F16: =IF(Hackathons!AH43="","",Hackathons!AH43) -> 1 | G16: =IF(Hackathons!AI43="","",Hackathons!AI43) -> Per Team | H16: =IF(Hackathons!S43="","",IF(G16="Per Team Member",Hackathons!S43*F16,Hackathons!S43)) | I16: =IF(Hackathons!T43="","",Hackathons!T43) | J16: =IF(OR(H16="",F16=""),"",H16/F16) | K16: =IF(Hackathons!U43="","",IF(G16="Per Team Member",Hackathons!U43*F16,Hackathons!U43)) -> 500 | L16: =IF(Hackathons!V43="","",Hackathons!V43) -> USD | M16: =IF(OR(K16="",F16=""),"",K16/F16) -> 500 | N16: =IF(Hackathons!W43="","",IF(G16="Per Team Member",Hackathons!W43*F16,Hackathons!W43)) | O16: =IF(Hackathons!X43="","",IF(G16="Per Team Member",Hackathons!X43*F16,Hackathons!X43)) | P16: =IF(Hackathons!Y43="","",Hackathons!Y43) | Q16: =IF(OR(O16="",F16=""),"",O16/F16) | R16: =IF(Hackathons!AC43="","",IF(G16="Per Team Member",Hackathons!AC43*F16,Hackathons!AC43)) | S16: =IF(Hackathons!AD43="","",Hackathons!AD43) | T16: =IF(OR(R16="",F16="",F16=0),"",R16/F16) | U16: =IF(Hackathons!Z43="","",Hackathons!Z43) -> Nosana Cloud credit | V16: =IF(Hackathons!AA43="","",Hackathons!AA43) | W16: =IF(Hackathons!AB43="","",Hackathons!AB43) | X16: =IF(Hackathons!AE43="","",Hackathons!AE43) -> Exclude | Y16: =IF(Hackathons!AF43="","",Hackathons!AF43) -> Cloud credit, not cash
A17: =Hackathons!A51 -> 50 | B17: =Hackathons!B51 -> Agentfield Hackathon 2026 | C17: =Hackathons!AG51 -> 1st Place — US$1,000 OpenRouter Credits | D17: =IF(Hackathons!Q51="","",Hackathons!Q51) -> 1st Prize | E17: =IF(Hackathons!R51="","",Hackathons!R51) | F17: =IF(Hackathons!AH51="","",Hackathons!AH51) -> 3 | G17: =IF(Hackathons!AI51="","",Hackathons!AI51) -> Per Team | H17: =IF(Hackathons!S51="","",IF(G17="Per Team Member",Hackathons!S51*F17,Hackathons!S51)) | I17: =IF(Hackathons!T51="","",Hackathons!T51) | J17: =IF(OR(H17="",F17=""),"",H17/F17) | K17: =IF(Hackathons!U51="","",IF(G17="Per Team Member",Hackathons!U51*F17,Hackathons!U51)) -> 1000 | L17: =IF(Hackathons!V51="","",Hackathons!V51) -> USD | M17: =IF(OR(K17="",F17=""),"",K17/F17) -> 333.33333 | N17: =IF(Hackathons!W51="","",IF(G17="Per Team Member",Hackathons!W51*F17,Hackathons!W51)) | O17: =IF(Hackathons!X51="","",IF(G17="Per Team Member",Hackathons!X51*F17,Hackathons!X51)) | P17: =IF(Hackathons!Y51="","",Hackathons!Y51) | Q17: =IF(OR(O17="",F17=""),"",O17/F17) | R17: =IF(Hackathons!AC51="","",IF(G17="Per Team Member",Hackathons!AC51*F17,Hackathons!AC51)) | S17: =IF(Hackathons!AD51="","",Hackathons!AD51) | T17: =IF(OR(R17="",F17="",F17=0),"",R17/F17) | U17: =IF(Hackathons!Z51="","",Hackathons!Z51) -> OpenRouter credits | V17: =IF(Hackathons!AA51="","",Hackathons!AA51) | W17: =IF(Hackathons!AB51="","",Hackathons!AB51) | X17: =IF(Hackathons!AE51="","",Hackathons!AE51) -> Exclude | Y17: =IF(Hackathons!AF51="","",Hackathons!AF51) -> API credits, not cash
A18: =Hackathons!A53 -> 52 | B18: =Hackathons!B53 -> AgentForce Hackathon 2026 | C18: =Hackathons!AG53 -> 1st Place — US$500 API Credits | D18: =IF(Hackathons!Q53="","",Hackathons!Q53) -> 1st Prize | E18: =IF(Hackathons!R53="","",Hackathons!R53) | F18: =IF(Hackathons!AH53="","",Hackathons!AH53) -> 3 | G18: =IF(Hackathons!AI53="","",Hackathons!AI53) -> Per Team | H18: =IF(Hackathons!S53="","",IF(G18="Per Team Member",Hackathons!S53*F18,Hackathons!S53)) | I18: =IF(Hackathons!T53="","",Hackathons!T53) | J18: =IF(OR(H18="",F18=""),"",H18/F18) | K18: =IF(Hackathons!U53="","",IF(G18="Per Team Member",Hackathons!U53*F18,Hackathons!U53)) -> 500 | L18: =IF(Hackathons!V53="","",Hackathons!V53) -> USD | M18: =IF(OR(K18="",F18=""),"",K18/F18) -> 166.66667 | N18: =IF(Hackathons!W53="","",IF(G18="Per Team Member",Hackathons!W53*F18,Hackathons!W53)) | O18: =IF(Hackathons!X53="","",IF(G18="Per Team Member",Hackathons!X53*F18,Hackathons!X53)) | P18: =IF(Hackathons!Y53="","",Hackathons!Y53) | Q18: =IF(OR(O18="",F18=""),"",O18/F18) | R18: =IF(Hackathons!AC53="","",IF(G18="Per Team Member",Hackathons!AC53*F18,Hackathons!AC53)) | S18: =IF(Hackathons!AD53="","",Hackathons!AD53) | T18: =IF(OR(R18="",F18="",F18=0),"",R18/F18) | U18: =IF(Hackathons!Z53="","",Hackathons!Z53) -> API credits | V18: =IF(Hackathons!AA53="","",Hackathons!AA53) | W18: =IF(Hackathons!AB53="","",Hackathons!AB53) | X18: =IF(Hackathons!AE53="","",Hackathons!AE53) -> Exclude | Y18: =IF(Hackathons!AF53="","",Hackathons!AF53) -> API credits, not cash
A19: =Hackathons!A54 -> 53 | B19: =Hackathons!B54 -> AgentForce Hackathon 2026 | C19: =Hackathons!AG54 -> 1st Place — US$500 API Credits | D19: =IF(Hackathons!Q54="","",Hackathons!Q54) -> 1st Prize | E19: =IF(Hackathons!R54="","",Hackathons!R54) | F19: =IF(Hackathons!AH54="","",Hackathons!AH54) -> 3 | G19: =IF(Hackathons!AI54="","",Hackathons!AI54) -> Per Team | H19: =IF(Hackathons!S54="","",IF(G19="Per Team Member",Hackathons!S54*F19,Hackathons!S54)) | I19: =IF(Hackathons!T54="","",Hackathons!T54) | J19: =IF(OR(H19="",F19=""),"",H19/F19) | K19: =IF(Hackathons!U54="","",IF(G19="Per Team Member",Hackathons!U54*F19,Hackathons!U54)) -> 500 | L19: =IF(Hackathons!V54="","",Hackathons!V54) -> USD | M19: =IF(OR(K19="",F19=""),"",K19/F19) -> 166.66667 | N19: =IF(Hackathons!W54="","",IF(G19="Per Team Member",Hackathons!W54*F19,Hackathons!W54)) | O19: =IF(Hackathons!X54="","",IF(G19="Per Team Member",Hackathons!X54*F19,Hackathons!X54)) | P19: =IF(Hackathons!Y54="","",Hackathons!Y54) | Q19: =IF(OR(O19="",F19=""),"",O19/F19) | R19: =IF(Hackathons!AC54="","",IF(G19="Per Team Member",Hackathons!AC54*F19,Hackathons!AC54)) | S19: =IF(Hackathons!AD54="","",Hackathons!AD54) | T19: =IF(OR(R19="",F19="",F19=0),"",R19/F19) | U19: =IF(Hackathons!Z54="","",Hackathons!Z54) -> API credits | V19: =IF(Hackathons!AA54="","",Hackathons!AA54) | W19: =IF(Hackathons!AB54="","",Hackathons!AB54) | X19: =IF(Hackathons!AE54="","",Hackathons!AE54) -> Exclude | Y19: =IF(Hackathons!AF54="","",Hackathons!AF54) -> API credits, not cash
A20: =Hackathons!A55 -> 54 | B20: =Hackathons!B55 -> SUSS X Openclaw Hackathon 2026 | C20: =Hackathons!AG55 -> 1st Place — US$150 Wavespeed AI Credits | D20: =IF(Hackathons!Q55="","",Hackathons!Q55) -> 1st Prize | E20: =IF(Hackathons!R55="","",Hackathons!R55) | F20: =IF(Hackathons!AH55="","",Hackathons!AH55) -> 3 | G20: =IF(Hackathons!AI55="","",Hackathons!AI55) -> Per Team | H20: =IF(Hackathons!S55="","",IF(G20="Per Team Member",Hackathons!S55*F20,Hackathons!S55)) | I20: =IF(Hackathons!T55="","",Hackathons!T55) | J20: =IF(OR(H20="",F20=""),"",H20/F20) | K20: =IF(Hackathons!U55="","",IF(G20="Per Team Member",Hackathons!U55*F20,Hackathons!U55)) -> 150 | L20: =IF(Hackathons!V55="","",Hackathons!V55) -> USD | M20: =IF(OR(K20="",F20=""),"",K20/F20) -> 50 | N20: =IF(Hackathons!W55="","",IF(G20="Per Team Member",Hackathons!W55*F20,Hackathons!W55)) | O20: =IF(Hackathons!X55="","",IF(G20="Per Team Member",Hackathons!X55*F20,Hackathons!X55)) | P20: =IF(Hackathons!Y55="","",Hackathons!Y55) | Q20: =IF(OR(O20="",F20=""),"",O20/F20) | R20: =IF(Hackathons!AC55="","",IF(G20="Per Team Member",Hackathons!AC55*F20,Hackathons!AC55)) | S20: =IF(Hackathons!AD55="","",Hackathons!AD55) | T20: =IF(OR(R20="",F20="",F20=0),"",R20/F20) | U20: =IF(Hackathons!Z55="","",Hackathons!Z55) -> Wavespeed AI credits | V20: =IF(Hackathons!AA55="","",Hackathons!AA55) | W20: =IF(Hackathons!AB55="","",Hackathons!AB55) | X20: =IF(Hackathons!AE55="","",Hackathons!AE55) -> Exclude | Y20: =IF(Hackathons!AF55="","",Hackathons!AF55) -> API credits, not cash
A21: =Hackathons!A58 -> 57 | B21: =Hackathons!B58 -> Agora.io Voice AI Hackathon Singapore 2026 | C21: =Hackathons!AG58 -> 3rd Place — S$300 Cash + S$385 API Credits | D21: =IF(Hackathons!Q58="","",Hackathons!Q58) -> 3rd Prize | E21: =IF(Hackathons!R58="","",Hackathons!R58) | F21: =IF(Hackathons!AH58="","",Hackathons!AH58) -> 1 | G21: =IF(Hackathons!AI58="","",Hackathons!AI58) -> Per Team | H21: =IF(Hackathons!S58="","",IF(G21="Per Team Member",Hackathons!S58*F21,Hackathons!S58)) -> 300 | I21: =IF(Hackathons!T58="","",Hackathons!T58) -> SGD | J21: =IF(OR(H21="",F21=""),"",H21/F21) -> 300 | K21: =IF(Hackathons!U58="","",IF(G21="Per Team Member",Hackathons!U58*F21,Hackathons!U58)) -> 385 | L21: =IF(Hackathons!V58="","",Hackathons!V58) -> SGD | M21: =IF(OR(K21="",F21=""),"",K21/F21) -> 385 | N21: =IF(Hackathons!W58="","",IF(G21="Per Team Member",Hackathons!W58*F21,Hackathons!W58)) | O21: =IF(Hackathons!X58="","",IF(G21="Per Team Member",Hackathons!X58*F21,Hackathons!X58)) | P21: =IF(Hackathons!Y58="","",Hackathons!Y58) | Q21: =IF(OR(O21="",F21=""),"",O21/F21) | R21: =IF(Hackathons!AC58="","",IF(G21="Per Team Member",Hackathons!AC58*F21,Hackathons!AC58)) | S21: =IF(Hackathons!AD58="","",Hackathons!AD58) | T21: =IF(OR(R21="",F21="",F21=0),"",R21/F21) | U21: =IF(Hackathons!Z58="","",Hackathons!Z58) -> API credits | V21: =IF(Hackathons!AA58="","",Hackathons!AA58) | W21: =IF(Hackathons!AB58="","",Hackathons!AB58) | X21: =IF(Hackathons!AE58="","",Hackathons!AE58) -> Yes | Y21: =IF(Hackathons!AF58="","",Hackathons!AF58) -> Explicit cash; API credit value also tracked
A22: =Hackathons!A61 -> 60 | B22: =Hackathons!B61 -> Build Voice Agents with Speechmatics | TGB Buildathon 2026 | C22: =Hackathons!AG61 -> Award — Speechmatics — US$2,000 Speechmatics Credits | D22: =IF(Hackathons!Q61="","",Hackathons!Q61) -> Award | E22: =IF(Hackathons!R61="","",Hackathons!R61) -> Speechmatics | F22: =IF(Hackathons!AH61="","",Hackathons!AH61) -> 1 | G22: =IF(Hackathons!AI61="","",Hackathons!AI61) -> Per Team | H22: =IF(Hackathons!S61="","",IF(G22="Per Team Member",Hackathons!S61*F22,Hackathons!S61)) | I22: =IF(Hackathons!T61="","",Hackathons!T61) | J22: =IF(OR(H22="",F22=""),"",H22/F22) | K22: =IF(Hackathons!U61="","",IF(G22="Per Team Member",Hackathons!U61*F22,Hackathons!U61)) -> 2000 | L22: =IF(Hackathons!V61="","",Hackathons!V61) -> USD | M22: =IF(OR(K22="",F22=""),"",K22/F22) -> 2000 | N22: =IF(Hackathons!W61="","",IF(G22="Per Team Member",Hackathons!W61*F22,Hackathons!W61)) | O22: =IF(Hackathons!X61="","",IF(G22="Per Team Member",Hackathons!X61*F22,Hackathons!X61)) | P22: =IF(Hackathons!Y61="","",Hackathons!Y61) | Q22: =IF(OR(O22="",F22=""),"",O22/F22) | R22: =IF(Hackathons!AC61="","",IF(G22="Per Team Member",Hackathons!AC61*F22,Hackathons!AC61)) | S22: =IF(Hackathons!AD61="","",Hackathons!AD61) | T22: =IF(OR(R22="",F22="",F22=0),"",R22/F22) | U22: =IF(Hackathons!Z61="","",Hackathons!Z61) -> Speechmatics credits | V22: =IF(Hackathons!AA61="","",Hackathons!AA61) | W22: =IF(Hackathons!AB61="","",Hackathons!AB61) | X22: =IF(Hackathons!AE61="","",Hackathons!AE61) -> Exclude | Y22: =IF(Hackathons!AF61="","",Hackathons!AF61) -> USD-denominated credit value
A23: =Hackathons!A62 -> 61 | B23: =Hackathons!B62 -> Vercel Zero to Agent: Singapore (1 Hr Hackathon) 2026 | C23: =Hackathons!AG62 -> 2nd Place — v0 Sock | D23: =IF(Hackathons!Q62="","",Hackathons!Q62) -> 2nd Place | E23: =IF(Hackathons!R62="","",Hackathons!R62) -> v0 Sock | F23: =IF(Hackathons!AH62="","",Hackathons!AH62) -> 1 | G23: =IF(Hackathons!AI62="","",Hackathons!AI62) -> Per Team | H23: =IF(Hackathons!S62="","",IF(G23="Per Team Member",Hackathons!S62*F23,Hackathons!S62)) | I23: =IF(Hackathons!T62="","",Hackathons!T62) | J23: =IF(OR(H23="",F23=""),"",H23/F23) | K23: =IF(Hackathons!U62="","",IF(G23="Per Team Member",Hackathons!U62*F23,Hackathons!U62)) | L23: =IF(Hackathons!V62="","",Hackathons!V62) | M23: =IF(OR(K23="",F23=""),"",K23/F23) | N23: =IF(Hackathons!W62="","",IF(G23="Per Team Member",Hackathons!W62*F23,Hackathons!W62)) | O23: =IF(Hackathons!X62="","",IF(G23="Per Team Member",Hackathons!X62*F23,Hackathons!X62)) | P23: =IF(Hackathons!Y62="","",Hackathons!Y62) | Q23: =IF(OR(O23="",F23=""),"",O23/F23) | R23: =IF(Hackathons!AC62="","",IF(G23="Per Team Member",Hackathons!AC62*F23,Hackathons!AC62)) | S23: =IF(Hackathons!AD62="","",Hackathons!AD62) | T23: =IF(OR(R23="",F23="",F23=0),"",R23/F23) | U23: =IF(Hackathons!Z62="","",Hackathons!Z62) -> v0 Sock | V23: =IF(Hackathons!AA62="","",Hackathons!AA62) -> v0 Sock | W23: =IF(Hackathons!AB62="","",Hackathons!AB62) -> 0 | X23: =IF(Hackathons!AE62="","",Hackathons!AE62) -> Exclude | Y23: =IF(Hackathons!AF62="","",Hackathons!AF62) -> Physical item, not cash
A24: =Hackathons!A67 -> 66 | B24: =Hackathons!B67 -> UCWS 2026 (Semi-Finals) | C24: =Hackathons!AG67 -> Top 20 — US$12,000 Credits (OpenAI + Gemini Cloud) | D24: =IF(Hackathons!Q67="","",Hackathons!Q67) -> Top 20 | E24: =IF(Hackathons!R67="","",Hackathons!R67) | F24: =IF(Hackathons!AH67="","",Hackathons!AH67) -> 2 | G24: =IF(Hackathons!AI67="","",Hackathons!AI67) -> Per Team | H24: =IF(Hackathons!S67="","",IF(G24="Per Team Member",Hackathons!S67*F24,Hackathons!S67)) | I24: =IF(Hackathons!T67="","",Hackathons!T67) | J24: =IF(OR(H24="",F24=""),"",H24/F24) | K24: =IF(Hackathons!U67="","",IF(G24="Per Team Member",Hackathons!U67*F24,Hackathons!U67)) -> 12000 | L24: =IF(Hackathons!V67="","",Hackathons!V67) -> USD | M24: =IF(OR(K24="",F24=""),"",K24/F24) -> 6000 | N24: =IF(Hackathons!W67="","",IF(G24="Per Team Member",Hackathons!W67*F24,Hackathons!W67)) | O24: =IF(Hackathons!X67="","",IF(G24="Per Team Member",Hackathons!X67*F24,Hackathons!X67)) | P24: =IF(Hackathons!Y67="","",Hackathons!Y67) | Q24: =IF(OR(O24="",F24=""),"",O24/F24) | R24: =IF(Hackathons!AC67="","",IF(G24="Per Team Member",Hackathons!AC67*F24,Hackathons!AC67)) | S24: =IF(Hackathons!AD67="","",Hackathons!AD67) | T24: =IF(OR(R24="",F24="",F24=0),"",R24/F24) | U24: =IF(Hackathons!Z67="","",Hackathons!Z67) -> 10K OpenAI credits; 2K Gemini Cloud credits | V24: =IF(Hackathons!AA67="","",Hackathons!AA67) | W24: =IF(Hackathons!AB67="","",Hackathons!AB67) | X24: =IF(Hackathons!AE67="","",Hackathons!AE67) -> Exclude | Y24: =IF(Hackathons!AF67="","",Hackathons!AF67) -> Credit value total combines two USD-denominated credits
A25: =Hackathons!A72 -> 71 | B25: =Hackathons!B72 -> BUIDL_OPC_Hackathon_SG | C25: =Hackathons!AG72 -> Top 30 — US$4,500 AWS Credits | D25: =IF(Hackathons!Q72="","",Hackathons!Q72) -> Top 30 | E25: =IF(Hackathons!R72="","",Hackathons!R72) | F25: =IF(Hackathons!AH72="","",Hackathons!AH72) -> 2 | G25: =IF(Hackathons!AI72="","",Hackathons!AI72) -> Per Team | H25: =IF(Hackathons!S72="","",IF(G25="Per Team Member",Hackathons!S72*F25,Hackathons!S72)) | I25: =IF(Hackathons!T72="","",Hackathons!T72) | J25: =IF(OR(H25="",F25=""),"",H25/F25) | K25: =IF(Hackathons!U72="","",IF(G25="Per Team Member",Hackathons!U72*F25,Hackathons!U72)) -> 4500 | L25: =IF(Hackathons!V72="","",Hackathons!V72) -> USD | M25: =IF(OR(K25="",F25=""),"",K25/F25) -> 2250 | N25: =IF(Hackathons!W72="","",IF(G25="Per Team Member",Hackathons!W72*F25,Hackathons!W72)) | O25: =IF(Hackathons!X72="","",IF(G25="Per Team Member",Hackathons!X72*F25,Hackathons!X72)) | P25: =IF(Hackathons!Y72="","",Hackathons!Y72) | Q25: =IF(OR(O25="",F25=""),"",O25/F25) | R25: =IF(Hackathons!AC72="","",IF(G25="Per Team Member",Hackathons!AC72*F25,Hackathons!AC72)) | S25: =IF(Hackathons!AD72="","",Hackathons!AD72) | T25: =IF(OR(R25="",F25="",F25=0),"",R25/F25) | U25: =IF(Hackathons!Z72="","",Hackathons!Z72) -> AWS credits | V25: =IF(Hackathons!AA72="","",Hackathons!AA72) | W25: =IF(Hackathons!AB72="","",Hackathons!AB72) | X25: =IF(Hackathons!AE72="","",Hackathons!AE72) -> Exclude | Y25: =IF(Hackathons!AF72="","",Hackathons!AF72) -> USD-denominated credit value
A26: =Hackathons!A76 -> 75 | B26: =Hackathons!B76 -> One AI Hackathon 2026 | C26: =Hackathons!AG76 -> Best Project — Best Vertical Solution: Family Office Track — 2,000 Cybrdeck API Credits Each (US$25 value) | D26: =IF(Hackathons!Q76="","",Hackathons!Q76) -> Best Project | E26: =IF(Hackathons!R76="","",Hackathons!R76) -> Best Vertical Solution: Family Office Track | F26: =IF(Hackathons!AH76="","",Hackathons!AH76) -> 2 | G26: =IF(Hackathons!AI76="","",Hackathons!AI76) -> Per Team Member | H26: =IF(Hackathons!S76="","",IF(G26="Per Team Member",Hackathons!S76*F26,Hackathons!S76)) | I26: =IF(Hackathons!T76="","",Hackathons!T76) | J26: =IF(OR(H26="",F26=""),"",H26/F26) | K26: =IF(Hackathons!U76="","",IF(G26="Per Team Member",Hackathons!U76*F26,Hackathons!U76)) -> 50 | L26: =IF(Hackathons!V76="","",Hackathons!V76) -> USD | M26: =IF(OR(K26="",F26=""),"",K26/F26) -> 25 | N26: =IF(Hackathons!W76="","",IF(G26="Per Team Member",Hackathons!W76*F26,Hackathons!W76)) | O26: =IF(Hackathons!X76="","",IF(G26="Per Team Member",Hackathons!X76*F26,Hackathons!X76)) | P26: =IF(Hackathons!Y76="","",Hackathons!Y76) | Q26: =IF(OR(O26="",F26=""),"",O26/F26) | R26: =IF(Hackathons!AC76="","",IF(G26="Per Team Member",Hackathons!AC76*F26,Hackathons!AC76)) | S26: =IF(Hackathons!AD76="","",Hackathons!AD76) | T26: =IF(OR(R26="",F26="",F26=0),"",R26/F26) | U26: =IF(Hackathons!Z76="","",Hackathons!Z76) -> 2,000 Cybrdeck API credits | V26: =IF(Hackathons!AA76="","",Hackathons!AA76) | W26: =IF(Hackathons!AB76="","",Hackathons!AB76) | X26: =IF(Hackathons!AE76="","",Hackathons!AE76) -> Exclude | Y26: =IF(Hackathons!AF76="","",Hackathons!AF76) -> US$25 credit value, not cash
A27: =Hackathons!A80 -> 79 | B27: =Hackathons!B80 -> SG × SWK Friendship AI Business Design Hackathon | C27: =Hackathons!AG80 -> First Runner-Up — SG × Sarawak AI & Design Hackathon — US$200 Kimi AI Credits + Trophy | D27: =IF(Hackathons!Q80="","",Hackathons!Q80) -> First Runner-Up | E27: =IF(Hackathons!R80="","",Hackathons!R80) -> SG × Sarawak AI & Design Hackathon 2026 | F27: =IF(Hackathons!AH80="","",Hackathons!AH80) -> 3 | G27: =IF(Hackathons!AI80="","",Hackathons!AI80) -> Per Team | H27: =IF(Hackathons!S80="","",IF(G27="Per Team Member",Hackathons!S80*F27,Hackathons!S80)) | I27: =IF(Hackathons!T80="","",Hackathons!T80) | J27: =IF(OR(H27="",F27=""),"",H27/F27) | K27: =IF(Hackathons!U80="","",IF(G27="Per Team Member",Hackathons!U80*F27,Hackathons!U80)) -> 200 | L27: =IF(Hackathons!V80="","",Hackathons!V80) -> USD | M27: =IF(OR(K27="",F27=""),"",K27/F27) -> 66.666667 | N27: =IF(Hackathons!W80="","",IF(G27="Per Team Member",Hackathons!W80*F27,Hackathons!W80)) | O27: =IF(Hackathons!X80="","",IF(G27="Per Team Member",Hackathons!X80*F27,Hackathons!X80)) | P27: =IF(Hackathons!Y80="","",Hackathons!Y80) | Q27: =IF(OR(O27="",F27=""),"",O27/F27) | R27: =IF(Hackathons!AC80="","",IF(G27="Per Team Member",Hackathons!AC80*F27,Hackathons!AC80)) | S27: =IF(Hackathons!AD80="","",Hackathons!AD80) | T27: =IF(OR(R27="",F27="",F27=0),"",R27/F27) | U27: =IF(Hackathons!Z80="","",Hackathons!Z80) -> Trophy; Kimi AI credits | V27: =IF(Hackathons!AA80="","",Hackathons!AA80) -> Trophy | W27: =IF(Hackathons!AB80="","",Hackathons!AB80) -> 1 | X27: =IF(Hackathons!AE80="","",Hackathons!AE80) -> Exclude | Y27: =IF(Hackathons!AF80="","",Hackathons!AF80) -> Trophy excluded; credit value tracked
A28: =Hackathons!A81 -> 80 | B28: =Hackathons!B81 -> GPT-6 Astra Hackathon: Singapore | C28: =Hackathons!AG81 -> Best Project — Best Use of GPT-Image-2.5 — US$5,000 OpenAI Credits Each | D28: =IF(Hackathons!Q81="","",Hackathons!Q81) -> Best Project | E28: =IF(Hackathons!R81="","",Hackathons!R81) -> Best Use of GPT-Image-2.5 | F28: =IF(Hackathons!AH81="","",Hackathons!AH81) -> 2 | G28: =IF(Hackathons!AI81="","",Hackathons!AI81) -> Per Team Member | H28: =IF(Hackathons!S81="","",IF(G28="Per Team Member",Hackathons!S81*F28,Hackathons!S81)) | I28: =IF(Hackathons!T81="","",Hackathons!T81) | J28: =IF(OR(H28="",F28=""),"",H28/F28) | K28: =IF(Hackathons!U81="","",IF(G28="Per Team Member",Hackathons!U81*F28,Hackathons!U81)) -> 10000 | L28: =IF(Hackathons!V81="","",Hackathons!V81) -> USD | M28: =IF(OR(K28="",F28=""),"",K28/F28) -> 5000 | N28: =IF(Hackathons!W81="","",IF(G28="Per Team Member",Hackathons!W81*F28,Hackathons!W81)) | O28: =IF(Hackathons!X81="","",IF(G28="Per Team Member",Hackathons!X81*F28,Hackathons!X81)) | P28: =IF(Hackathons!Y81="","",Hackathons!Y81) | Q28: =IF(OR(O28="",F28=""),"",O28/F28) | R28: =IF(Hackathons!AC81="","",IF(G28="Per Team Member",Hackathons!AC81*F28,Hackathons!AC81)) | S28: =IF(Hackathons!AD81="","",Hackathons!AD81) | T28: =IF(OR(R28="",F28="",F28=0),"",R28/F28) | U28: =IF(Hackathons!Z81="","",Hackathons!Z81) -> OpenAI credits | V28: =IF(Hackathons!AA81="","",Hackathons!AA81) | W28: =IF(Hackathons!AB81="","",Hackathons!AB81) | X28: =IF(Hackathons!AE81="","",Hackathons!AE81) -> Exclude | Y28: =IF(Hackathons!AF81="","",Hackathons!AF81) -> Credit value tracked
